{
  "displayFieldName": "Agency",
  "fieldAliases": {
    "UID": "UID",
    "Agency": "Agency",
    "Address": "Address",
    "CrossStreet": "CrossStreet",
    "CALL_TIME": "CALL_TIME",
    "IncidentType": "IncidentType",
    "ALARM_LEVEL": "ALARM_LEVEL",
    "NO_UNITS": "NO_UNITS",
    "Units": "Units",
    "LONGITUDE": "LONGITUDE",
    "LATITUDE": "LATITUDE",
    "KeyMap": "KeyMap",
    "CombinedResponse": "CombinedResponse"
  },
  "fields": [
    {
      "name": "UID",
      "type": "esriFieldTypeOID",
      "alias": "UID"
    },
    {
      "name": "Agency",
      "type": "esriFieldTypeString",
      "alias": "Agency",
      "length": 50
    },
    {
      "name": "Address",
      "type": "esriFieldTypeString",
      "alias": "Address",
      "length": 300
    },
    {
      "name": "CrossStreet",
      "type": "esriFieldTypeString",
      "alias": "CrossStreet",
      "length": 300
    },
    {
      "name": "CALL_TIME",
      "type": "esriFieldTypeDate",
      "alias": "CALL_TIME",
      "length": 8
    },
    {
      "name": "IncidentType",
      "type": "esriFieldTypeString",
      "alias": "IncidentType",
      "length": 300
    },
    {
      "name": "ALARM_LEVEL",
      "type": "esriFieldTypeInteger",
      "alias": "ALARM_LEVEL"
    },
    {
      "name": "NO_UNITS",
      "type": "esriFieldTypeInteger",
      "alias": "NO_UNITS"
    },
    {
      "name": "Units",
      "type": "esriFieldTypeString",
      "alias": "Units",
      "length": 500
    },
    {
      "name": "LONGITUDE",
      "type": "esriFieldTypeDouble",
      "alias": "LONGITUDE"
    },
    {
      "name": "LATITUDE",
      "type": "esriFieldTypeDouble",
      "alias": "LATITUDE"
    },
    {
      "name": "KeyMap",
      "type": "esriFieldTypeString",
      "alias": "KeyMap",
      "length": 50
    },
    {
      "name": "CombinedResponse",
      "type": "esriFieldTypeString",
      "alias": "CombinedResponse",
      "length": 50
    }
  ],
  "features": [
    {
      "attributes": {
        "UID": 29825670,
        "Agency": "F",
        "Address": "SAXON DR",
        "CrossStreet": "BLK BOLIN RD",
        "CALL_TIME": 1703191320000,
        "IncidentType": "EMS EVENT",
        "ALARM_LEVEL": 0,
        "NO_UNITS": 1,
        "Units": "E050",
        "LONGITUDE": -95.481086,
        "LATITUDE": 29.82567,
        "KeyMap": "451K",
        "CombinedResponse": "F"
      }
    },
    {
      "attributes": {
        "UID": 29557327,
        "Agency": "F",
        "Address": "GULF FWY OB",
        "CrossStreet": "ACCESS ROAD EL DORADO BLVD",
        "CALL_TIME": 1703191320000,
        "IncidentType": "EMS EVENT",
        "ALARM_LEVEL": 0,
        "NO_UNITS": 1,
        "Units": "M094",
        "LONGITUDE": -95.158309,
        "LATITUDE": 29.557327,
        "KeyMap": "617Q",
        "CombinedResponse": "F"
      }
    },
    {
      "attributes": {
        "UID": 29745068,
        "Agency": "F",
        "Address": "GRAY ST",
        "CrossStreet": "BLK CHENEVERT ST",
        "CALL_TIME": 1703191320000,
        "IncidentType": "AUTOMATIC ALARM",
        "ALARM_LEVEL": 0,
        "NO_UNITS": 1,
        "Units": "E008",
        "LONGITUDE": -95.365313,
        "LATITUDE": 29.745068,
        "KeyMap": "493U",
        "CombinedResponse": "F"
      }
    },
    {
      "attributes": {
        "UID": 29713358,
        "Agency": "F",
        "Address": "DALE CARNEGIE LN",
        "CrossStreet": "BLK REGENCY SQUARE BLVD",
        "CALL_TIME": 1703191320000,
        "IncidentType": "EMS EVENT",
        "ALARM_LEVEL": 0,
        "NO_UNITS": 3,
        "Units": "A060,M075,E051",
        "LONGITUDE": -95.504645,
        "LATITUDE": 29.713358,
        "KeyMap": "530D",
        "CombinedResponse": "F"
      }
    },
    {
      "attributes": {
        "UID": 29759385,
        "Agency": "F",
        "Address": "LOCKWOOD DR",
        "CrossStreet": "AMERICAN ST",
        "CALL_TIME": 1703191260000,
        "IncidentType": "EMS EVENT",
        "ALARM_LEVEL": 0,
        "NO_UNITS": 1,
        "Units": "M017",
        "LONGITUDE": -95.317903,
        "LATITUDE": 29.759385,
        "KeyMap": "494L",
        "CombinedResponse": "F"
      }
    },
    {
      "attributes": {
        "UID": 29826599,
        "Agency": "F",
        "Address": "GARDENIA DR",
        "CrossStreet": "BLK PINEY WOODS DR",
        "CALL_TIME": 1703191260000,
        "IncidentType": "EMS EVENT",
        "ALARM_LEVEL": 0,
        "NO_UNITS": 1,
        "Units": "A015",
        "LONGITUDE": -95.438951,
        "LATITUDE": 29.826599,
        "KeyMap": "452J",
        "CombinedResponse": "F"
      }
    },
    {
      "attributes": {
        "UID": 29966088,
        "Agency": "P",
        "Address": "17107 EASTEX FWY IB",
        "CrossStreet": null,
        "CALL_TIME": 1703191140000,
        "IncidentType": "TRAFFIC HAZARD/URGENT",
        "ALARM_LEVEL": 0,
        "NO_UNITS": 2,
        "Units": "22B40E,22B38E",
        "LONGITUDE": -95.284766,
        "LATITUDE": 29.966088,
        "KeyMap": "375F",
        "CombinedResponse": "P"
      }
    },
    {
      "attributes": {
        "UID": 29657835,
        "Agency": "F",
        "Address": "AIRPORT BLVD",
        "CrossStreet": "HOBBY AIRPORT LOOP RAMP",
        "CALL_TIME": 1703191140000,
        "IncidentType": "EMS EVENT",
        "ALARM_LEVEL": 0,
        "NO_UNITS": 1,
        "Units": "MS081",
        "LONGITUDE": -95.278492,
        "LATITUDE": 29.657835,
        "KeyMap": "575B",
        "CombinedResponse": "F"
      }
    },
    {
      "attributes": {
        "UID": 29717508,
        "Agency": "F",
        "Address": "HOOTON DR",
        "CrossStreet": "BLK PRESTWOOD DR",
        "CALL_TIME": 1703191140000,
        "IncidentType": "EMS EVENT",
        "ALARM_LEVEL": 0,
        "NO_UNITS": 2,
        "Units": "A051,M083",
        "LONGITUDE": -95.496071,
        "LATITUDE": 29.717508,
        "KeyMap": "531A",
        "CombinedResponse": "F"
      }
    },
    {
      "attributes": {
        "UID": 29819622,
        "Agency": "F",
        "Address": "W 34TH ST",
        "CrossStreet": null,
        "CALL_TIME": 1703191080000,
        "IncidentType": "EMS EVENT",
        "ALARM_LEVEL": 0,
        "NO_UNITS": 1,
        "Units": "A004",
        "LONGITUDE": -95.459451,
        "LATITUDE": 29.819622,
        "KeyMap": "451R",
        "CombinedResponse": "F"
      }
    },
    {
      "attributes": {
        "UID": 29740801,
        "Agency": "F",
        "Address": "WESTHEIMER RD",
        "CrossStreet": "BLK MCCUE RD",
        "CALL_TIME": 1703191020000,
        "IncidentType": "EMS EVENT",
        "ALARM_LEVEL": 0,
        "NO_UNITS": 1,
        "Units": "MPR028",
        "LONGITUDE": -95.461529,
        "LATITUDE": 29.740801,
        "KeyMap": "491U",
        "CombinedResponse": "F"
      }
    },
    {
      "attributes": {
        "UID": 29828243,
        "Agency": "F",
        "Address": "W 43RD ST",
        "CrossStreet": "BLK OAK FOREST DR",
        "CALL_TIME": 1703191020000,
        "IncidentType": "EMS EVENT",
        "ALARM_LEVEL": 0,
        "NO_UNITS": 2,
        "Units": "E013,A009",
        "LONGITUDE": -95.433615,
        "LATITUDE": 29.828243,
        "KeyMap": "452K",
        "CombinedResponse": "F"
      }
    },
    {
      "attributes": {
        "UID": 29680372,
        "Agency": "F",
        "Address": "SOUTHINGTON ST",
        "CrossStreet": "BLK CRESTMONT ST",
        "CALL_TIME": 1703191020000,
        "IncidentType": "EMS EVENT",
        "ALARM_LEVEL": 0,
        "NO_UNITS": 1,
        "Units": "E035",
        "LONGITUDE": -95.330897,
        "LATITUDE": 29.680372,
        "KeyMap": "534T",
        "CombinedResponse": "F"
      }
    },
    {
      "attributes": {
        "UID": 29715289,
        "Agency": "F",
        "Address": "FANNIN ST",
        "CrossStreet": "BLK JOHN FREEMAN BLVD",
        "CALL_TIME": 1703191020000,
        "IncidentType": "EMS EVENT",
        "ALARM_LEVEL": 0,
        "NO_UNITS": 2,
        "Units": "A533,M024",
        "LONGITUDE": -95.396595,
        "LATITUDE": 29.715289,
        "KeyMap": "533A",
        "CombinedResponse": "F"
      }
    },
    {
      "attributes": {
        "UID": 29677821,
        "Agency": "F",
        "Address": "CULLEN BLVD",
        "CrossStreet": "BLK MAYFLOWER ST",
        "CALL_TIME": 1703190960000,
        "IncidentType": "EMS EVENT",
        "ALARM_LEVEL": 0,
        "NO_UNITS": 1,
        "Units": "A524",
        "LONGITUDE": -95.355843,
        "LATITUDE": 29.677821,
        "KeyMap": "533V",
        "CombinedResponse": "F"
      }
    },
    {
      "attributes": {
        "UID": 29674293,
        "Agency": "F",
        "Address": "FORUM PARK DR",
        "CrossStreet": "BLK SUGAR BRANCH DR",
        "CALL_TIME": 1703190960000,
        "IncidentType": "EMS EVENT",
        "ALARM_LEVEL": 0,
        "NO_UNITS": 1,
        "Units": "E073",
        "LONGITUDE": -95.555074,
        "LATITUDE": 29.674293,
        "KeyMap": "529V",
        "CombinedResponse": "F"
      }
    },
    {
      "attributes": {
        "UID": 29785111,
        "Agency": "F",
        "Address": "KATY FWY OB",
        "CrossStreet": "GESSNER OBIB",
        "CALL_TIME": 1703190900000,
        "IncidentType": "EMS EVENT",
        "ALARM_LEVEL": 0,
        "NO_UNITS": 1,
        "Units": "M049",
        "LONGITUDE": -95.542256,
        "LATITUDE": 29.785111,
        "KeyMap": "490A",
        "CombinedResponse": "F"
      }
    },
    {
      "attributes": {
        "UID": 29730405,
        "Agency": "F",
        "Address": "ELGIN ST",
        "CrossStreet": null,
        "CALL_TIME": 1703190900000,
        "IncidentType": "EMS EVENT",
        "ALARM_LEVEL": 0,
        "NO_UNITS": 2,
        "Units": "E007,M019",
        "LONGITUDE": -95.35808,
        "LATITUDE": 29.730405,
        "KeyMap": "493Z",
        "CombinedResponse": "F"
      }
    },
    {
      "attributes": {
        "UID": 29785426,
        "Agency": "F",
        "Address": "KATY FWY OB",
        "CrossStreet": "BLK JORDEN RD",
        "CALL_TIME": 1703190840000,
        "IncidentType": "EMS EVENT",
        "ALARM_LEVEL": 0,
        "NO_UNITS": 1,
        "Units": "M078",
        "LONGITUDE": -95.629939,
        "LATITUDE": 29.785426,
        "KeyMap": "488B",
        "CombinedResponse": "F"
      }
    },
    {
      "attributes": {
        "UID": 29843856,
        "Agency": "F",
        "Address": "NORTHWEST FWY IB",
        "CrossStreet": "BLK LANGFIELD RD",
        "CALL_TIME": 1703190780000,
        "IncidentType": "EMS EVENT",
        "ALARM_LEVEL": 0,
        "NO_UNITS": 1,
        "Units": "M050",
        "LONGITUDE": -95.499144,
        "LATITUDE": 29.843856,
        "KeyMap": "451A",
        "CombinedResponse": "F"
      }
    },
    {
      "attributes": {
        "UID": 29733627,
        "Agency": "F",
        "Address": "YOAKUM BLVD",
        "CrossStreet": "DEAD-END",
        "CALL_TIME": 1703190540000,
        "IncidentType": "EMS EVENT",
        "ALARM_LEVEL": 0,
        "NO_UNITS": 2,
        "Units": "M018,A008",
        "LONGITUDE": -95.392477,
        "LATITUDE": 29.733627,
        "KeyMap": "493W",
        "CombinedResponse": "F"
      }
    },
    {
      "attributes": {
        "UID": 30046372,
        "Agency": "F",
        "Address": "LAZY GROVE DR",
        "CrossStreet": "BLK TRAILWOOD VILLAGE DR",
        "CALL_TIME": 1703190540000,
        "IncidentType": "EMS EVENT",
        "ALARM_LEVEL": 0,
        "NO_UNITS": 2,
        "Units": "E101,M102",
        "LONGITUDE": -95.225714,
        "LATITUDE": 30.046372,
        "KeyMap": "336C",
        "CombinedResponse": "F"
      }
    },
    {
      "attributes": {
        "UID": 29735910,
        "Agency": "F",
        "Address": "GULF FWY IB",
        "CrossStreet": "BLK SCOTT ST",
        "CALL_TIME": 1703190540000,
        "IncidentType": "EMS EVENT",
        "ALARM_LEVEL": 0,
        "NO_UNITS": 1,
        "Units": "E018",
        "LONGITUDE": -95.347118,
        "LATITUDE": 29.73591,
        "KeyMap": "494W",
        "CombinedResponse": "F"
      }
    },
    {
      "attributes": {
        "UID": 29946030,
        "Agency": "F",
        "Address": "GEARS RD",
        "CrossStreet": "BLK GREENS PKWY",
        "CALL_TIME": 1703190480000,
        "IncidentType": "EMS EVENT",
        "ALARM_LEVEL": 0,
        "NO_UNITS": 1,
        "Units": "A084",
        "LONGITUDE": -95.444502,
        "LATITUDE": 29.94603,
        "KeyMap": "372N",
        "CombinedResponse": "F"
      }
    },
    {
      "attributes": {
        "UID": 29824092,
        "Agency": "F",
        "Address": "LAMONTE LN",
        "CrossStreet": "BLK BOLIVIA BLVD",
        "CALL_TIME": 1703190360000,
        "IncidentType": "EMS EVENT",
        "ALARM_LEVEL": 0,
        "NO_UNITS": 1,
        "Units": "A067",
        "LONGITUDE": -95.464887,
        "LATITUDE": 29.824092,
        "KeyMap": "451L",
        "CombinedResponse": "F"
      }
    },
    {
      "attributes": {
        "UID": 29830001,
        "Agency": "F",
        "Address": "NORTH FWY OB",
        "CrossStreet": "CROSSTIMBERS IBOB",
        "CALL_TIME": 1703190240000,
        "IncidentType": "EMS EVENT",
        "ALARM_LEVEL": 0,
        "NO_UNITS": 1,
        "Units": "A012",
        "LONGITUDE": -95.377168,
        "LATITUDE": 29.830001,
        "KeyMap": "453K",
        "CombinedResponse": "F"
      }
    },
    {
      "attributes": {
        "UID": 29714056,
        "Agency": "F",
        "Address": "HERMANN PARK DR",
        "CrossStreet": "BLK CAMBRIDGE ST",
        "CALL_TIME": 1703190180000,
        "IncidentType": "EMS EVENT",
        "ALARM_LEVEL": 0,
        "NO_UNITS": 1,
        "Units": "A007",
        "LONGITUDE": -95.389286,
        "LATITUDE": 29.714056,
        "KeyMap": "533A",
        "CombinedResponse": "F"
      }
    },
    {
      "attributes": {
        "UID": 29651825,
        "Agency": "F",
        "Address": "CHIMNEY ROCK RD",
        "CrossStreet": "BLK GASMER DR",
        "CALL_TIME": 1703190180000,
        "IncidentType": "EMS EVENT",
        "ALARM_LEVEL": 0,
        "NO_UNITS": 2,
        "Units": "A037,M059",
        "LONGITUDE": -95.481376,
        "LATITUDE": 29.651825,
        "KeyMap": "571B",
        "CombinedResponse": "F"
      }
    },
    {
      "attributes": {
        "UID": 29538822,
        "Agency": "P",
        "Address": "1501 W BAY AREA BLVD",
        "CrossStreet": null,
        "CALL_TIME": 1703190120000,
        "IncidentType": "TRAFFIC HAZARD/URGENT",
        "ALARM_LEVEL": 0,
        "NO_UNITS": 1,
        "Units": "12D32E",
        "LONGITUDE": -95.145905,
        "LATITUDE": 29.538822,
        "KeyMap": "617Z",
        "CombinedResponse": "P"
      }
    },
    {
      "attributes": {
        "UID": 29898264,
        "Agency": "F",
        "Address": "W MOUNT HOUSTON RD",
        "CrossStreet": null,
        "CALL_TIME": 1703190060000,
        "IncidentType": "MOTOR VEHICLE INCIDENT",
        "ALARM_LEVEL": 0,
        "NO_UNITS": 2,
        "Units": "E084,A058",
        "LONGITUDE": -95.412619,
        "LATITUDE": 29.898264,
        "KeyMap": "412M",
        "CombinedResponse": "F"
      }
    },
    {
      "attributes": {
        "UID": 29747563,
        "Agency": "F",
        "Address": "SAN JACINTO ST",
        "CrossStreet": "BLK WEBSTER ST",
        "CALL_TIME": 1703190000000,
        "IncidentType": "EMS EVENT",
        "ALARM_LEVEL": 0,
        "NO_UNITS": 1,
        "Units": "A508",
        "LONGITUDE": -95.369809,
        "LATITUDE": 29.747563,
        "KeyMap": "493Q",
        "CombinedResponse": "F"
      }
    },
    {
      "attributes": {
        "UID": 29646473,
        "Agency": "F",
        "Address": "FONDREN RD",
        "CrossStreet": "BLK W AIRPORT BLVD",
        "CALL_TIME": 1703189940000,
        "IncidentType": "EMS EVENT",
        "ALARM_LEVEL": 0,
        "NO_UNITS": 1,
        "Units": "A573",
        "LONGITUDE": -95.508307,
        "LATITUDE": 29.646473,
        "KeyMap": "570G",
        "CombinedResponse": "F"
      }
    },
    {
      "attributes": {
        "UID": 29709832,
        "Agency": "F",
        "Address": "RANCHESTER DR",
        "CrossStreet": "BLK CLAREWOOD DR",
        "CALL_TIME": 1703189700000,
        "IncidentType": "EMS EVENT",
        "ALARM_LEVEL": 0,
        "NO_UNITS": 2,
        "Units": "SQ082,A076",
        "LONGITUDE": -95.545484,
        "LATITUDE": 29.709832,
        "KeyMap": "530E",
        "CombinedResponse": "F"
      }
    },
    {
      "attributes": {
        "UID": 29898264,
        "Agency": "P",
        "Address": "703 W MOUNT HOUSTON RD",
        "CrossStreet": null,
        "CALL_TIME": 1703189640000,
        "IncidentType": "CRASH/MAJOR/NON FATAL",
        "ALARM_LEVEL": 0,
        "NO_UNITS": 2,
        "Units": "6B40E,75Z22",
        "LONGITUDE": -95.412619,
        "LATITUDE": 29.898264,
        "KeyMap": "412M",
        "CombinedResponse": "P"
      }
    },
    {
      "attributes": {
        "UID": 29725581,
        "Agency": "F",
        "Address": "BISSONNET ST",
        "CrossStreet": null,
        "CALL_TIME": 1703189640000,
        "IncidentType": "EMS EVENT",
        "ALARM_LEVEL": 0,
        "NO_UNITS": 2,
        "Units": "SQ008,A016",
        "LONGITUDE": -95.410531,
        "LATITUDE": 29.725581,
        "KeyMap": "492Y",
        "CombinedResponse": "F"
      }
    },
    {
      "attributes": {
        "UID": 29737568,
        "Agency": "F",
        "Address": "WESTHEIMER RD",
        "CrossStreet": "BLK STONEY BROOK DR",
        "CALL_TIME": 1703189520000,
        "IncidentType": "EMS EVENT",
        "ALARM_LEVEL": 0,
        "NO_UNITS": 1,
        "Units": "A068",
        "LONGITUDE": -95.504318,
        "LATITUDE": 29.737568,
        "KeyMap": "490V",
        "CombinedResponse": "F"
      }
    },
    {
      "attributes": {
        "UID": 29627751,
        "Agency": "F",
        "Address": "E OREM DR",
        "CrossStreet": null,
        "CALL_TIME": 1703189460000,
        "IncidentType": "EMS EVENT",
        "ALARM_LEVEL": 0,
        "NO_UNITS": 2,
        "Units": "E047,A036",
        "LONGITUDE": -95.377997,
        "LATITUDE": 29.627751,
        "KeyMap": "573K",
        "CombinedResponse": "F"
      }
    },
    {
      "attributes": {
        "UID": 29671296,
        "Agency": "F",
        "Address": "BRICKER ST",
        "CrossStreet": "DEAD-END",
        "CALL_TIME": 1703189460000,
        "IncidentType": "EMS EVENT",
        "ALARM_LEVEL": 0,
        "NO_UNITS": 2,
        "Units": "SQ046,A055",
        "LONGITUDE": -95.350844,
        "LATITUDE": 29.671296,
        "KeyMap": "533V",
        "CombinedResponse": "F"
      }
    },
    {
      "attributes": {
        "UID": 29856843,
        "Agency": "F",
        "Address": "NORTHWEST FWY IB",
        "CrossStreet": "FAIRBANKS N HOUSTON ENTR",
        "CALL_TIME": 1703189400000,
        "IncidentType": "EMS EVENT",
        "ALARM_LEVEL": 0,
        "NO_UNITS": 2,
        "Units": "HME066,A005",
        "LONGITUDE": -95.521546,
        "LATITUDE": 29.856843,
        "KeyMap": "410Y",
        "CombinedResponse": "F"
      }
    },
    {
      "attributes": {
        "UID": 29749719,
        "Agency": "F",
        "Address": "EMANCIPATION AVE",
        "CrossStreet": null,
        "CALL_TIME": 1703189280000,
        "IncidentType": "MOTOR VEHICLE INCIDENT",
        "ALARM_LEVEL": 0,
        "NO_UNITS": 1,
        "Units": "A017",
        "LONGITUDE": -95.352927,
        "LATITUDE": 29.749719,
        "KeyMap": "493R",
        "CombinedResponse": "F"
      }
    },
    {
      "attributes": {
        "UID": 29627751,
        "Agency": "P",
        "Address": "2901 E OREM DR",
        "CrossStreet": null,
        "CALL_TIME": 1703189040000,
        "IncidentType": "CRASH/MAJOR/NON FATAL",
        "ALARM_LEVEL": 0,
        "NO_UNITS": 1,
        "Units": "13D24E",
        "LONGITUDE": -95.377997,
        "LATITUDE": 29.627751,
        "KeyMap": "573K",
        "CombinedResponse": "P"
      }
    },
    {
      "attributes": {
        "UID": 29748226,
        "Agency": "F",
        "Address": "BAYOU BROOK ST",
        "CrossStreet": "BLK DOLIVER DR",
        "CALL_TIME": 1703189040000,
        "IncidentType": "EMS EVENT",
        "ALARM_LEVEL": 0,
        "NO_UNITS": 1,
        "Units": "A083",
        "LONGITUDE": -95.537512,
        "LATITUDE": 29.748226,
        "KeyMap": "490N",
        "CombinedResponse": "F"
      }
    },
    {
      "attributes": {
        "UID": 29682233,
        "Agency": "F",
        "Address": "ALLENDALE RD",
        "CrossStreet": "BLK PEACH CREEK DR",
        "CALL_TIME": 1703188980000,
        "IncidentType": "EMS EVENT",
        "ALARM_LEVEL": 0,
        "NO_UNITS": 2,
        "Units": "E029,A023",
        "LONGITUDE": -95.251756,
        "LATITUDE": 29.682233,
        "KeyMap": "535V",
        "CombinedResponse": "F"
      }
    },
    {
      "attributes": {
        "UID": 29749719,
        "Agency": "P",
        "Address": "1001 EMANCIPATION AVE",
        "CrossStreet": null,
        "CALL_TIME": 1703188920000,
        "IncidentType": "CRASH/MAJOR/NON FATAL",
        "ALARM_LEVEL": 0,
        "NO_UNITS": 3,
        "Units": "10H67D,75Z41,10H34E",
        "LONGITUDE": -95.352927,
        "LATITUDE": 29.749719,
        "KeyMap": "493R",
        "CombinedResponse": "P"
      }
    },
    {
      "attributes": {
        "UID": 29740897,
        "Agency": "F",
        "Address": "GEORGIA ST",
        "CrossStreet": "BLK MIDWAY BLVD",
        "CALL_TIME": 1703188920000,
        "IncidentType": "EMS EVENT",
        "ALARM_LEVEL": 0,
        "NO_UNITS": 1,
        "Units": "M044",
        "LONGITUDE": -95.26212,
        "LATITUDE": 29.740897,
        "KeyMap": "495U",
        "CombinedResponse": "F"
      }
    },
    {
      "attributes": {
        "UID": 30048336,
        "Agency": "F",
        "Address": "PROFESSIONAL DR",
        "CrossStreet": "BLK KINGWOOD EXECUTIVE DR",
        "CALL_TIME": 1703188800000,
        "IncidentType": "EMS EVENT",
        "ALARM_LEVEL": 0,
        "NO_UNITS": 1,
        "Units": "M101",
        "LONGITUDE": -95.258176,
        "LATITUDE": 30.048336,
        "KeyMap": "335D",
        "CombinedResponse": "F"
      }
    },
    {
      "attributes": {
        "UID": 29677080,
        "Agency": "F",
        "Address": "S LOOP W",
        "CrossStreet": null,
        "CALL_TIME": 1703188740000,
        "IncidentType": "EMS EVENT",
        "ALARM_LEVEL": 0,
        "NO_UNITS": 1,
        "Units": "SQ033",
        "LONGITUDE": -95.424729,
        "LATITUDE": 29.67708,
        "KeyMap": "532T",
        "CombinedResponse": "F"
      }
    },
    {
      "attributes": {
        "UID": 29857355,
        "Agency": "F",
        "Address": "LANGFIELD RD",
        "CrossStreet": "BLK WILSHIRE PLACE DR",
        "CALL_TIME": 1703188680000,
        "IncidentType": "EMS EVENT",
        "ALARM_LEVEL": 0,
        "NO_UNITS": 1,
        "Units": "M067",
        "LONGITUDE": -95.500114,
        "LATITUDE": 29.857355,
        "KeyMap": "410Z",
        "CombinedResponse": "F"
      }
    },
    {
      "attributes": {
        "UID": 29951472,
        "Agency": "P",
        "Address": "15998 JOHN F KENNEDY BLVD OB",
        "CrossStreet": null,
        "CALL_TIME": 1703188620000,
        "IncidentType": "CRASH/MAJOR/NON FATAL",
        "ALARM_LEVEL": 0,
        "NO_UNITS": 2,
        "Units": "21I51D,21I52E",
        "LONGITUDE": -95.33139,
        "LATITUDE": 29.951472,
        "KeyMap": "374P",
        "CombinedResponse": "P"
      }
    },
    {
      "attributes": {
        "UID": 29685112,
        "Agency": "F",
        "Address": "JASON ST",
        "CrossStreet": "BLK S GESSNER RD",
        "CALL_TIME": 1703188440000,
        "IncidentType": "EMS EVENT",
        "ALARM_LEVEL": 0,
        "NO_UNITS": 2,
        "Units": "M073,A082",
        "LONGITUDE": -95.527686,
        "LATITUDE": 29.685112,
        "KeyMap": "530P",
        "CombinedResponse": "F"
      }
    },
    {
      "attributes": {
        "UID": 29823527,
        "Agency": "F",
        "Address": "ORIOLE ST",
        "CrossStreet": "BLK DISTRIBUTION BLVD",
        "CALL_TIME": 1703188320000,
        "IncidentType": "EMS EVENT",
        "ALARM_LEVEL": 0,
        "NO_UNITS": 1,
        "Units": "A013",
        "LONGITUDE": -95.402747,
        "LATITUDE": 29.823527,
        "KeyMap": "452M",
        "CombinedResponse": "F"
      }
    },
    {
      "attributes": {
        "UID": 29753723,
        "Agency": "F",
        "Address": "VALLEY FORGE DR",
        "CrossStreet": "BLK NANTUCKET DR",
        "CALL_TIME": 1703188020000,
        "IncidentType": "EMS EVENT",
        "ALARM_LEVEL": 0,
        "NO_UNITS": 1,
        "Units": "A503",
        "LONGITUDE": -95.486478,
        "LATITUDE": 29.753723,
        "KeyMap": "491N",
        "CombinedResponse": "F"
      }
    },
    {
      "attributes": {
        "UID": 29595825,
        "Agency": "F",
        "Address": "ALGONQUIN DR",
        "CrossStreet": "BLK NYACK DR",
        "CALL_TIME": 1703187900000,
        "IncidentType": "EMS EVENT",
        "ALARM_LEVEL": 0,
        "NO_UNITS": 1,
        "Units": "M036",
        "LONGITUDE": -95.197505,
        "LATITUDE": 29.595825,
        "KeyMap": "616D",
        "CombinedResponse": "F"
      }
    },
    {
      "attributes": {
        "UID": 29813898,
        "Agency": "F",
        "Address": "N SHEPHERD DR",
        "CrossStreet": null,
        "CALL_TIME": 1703187840000,
        "IncidentType": "EMS EVENT",
        "ALARM_LEVEL": 0,
        "NO_UNITS": 2,
        "Units": "M006,A011",
        "LONGITUDE": -95.410333,
        "LATITUDE": 29.813898,
        "KeyMap": "452R",
        "CombinedResponse": "F"
      }
    },
    {
      "attributes": {
        "UID": 29690534,
        "Agency": "F",
        "Address": "SCOTT ST",
        "CrossStreet": "BLK ALICE ST",
        "CALL_TIME": 1703187840000,
        "IncidentType": "EMS EVENT",
        "ALARM_LEVEL": 0,
        "NO_UNITS": 1,
        "Units": "A033",
        "LONGITUDE": -95.362895,
        "LATITUDE": 29.690534,
        "KeyMap": "533Q",
        "CombinedResponse": "F"
      }
    },
    {
      "attributes": {
        "UID": 29624749,
        "Agency": "F",
        "Address": "FS059 S POST OAK RD",
        "CrossStreet": "BLK PRUDENCE DR",
        "CALL_TIME": 1703187780000,
        "IncidentType": "EMS EVENT",
        "ALARM_LEVEL": 0,
        "NO_UNITS": 1,
        "Units": "A048",
        "LONGITUDE": -95.465124,
        "LATITUDE": 29.624749,
        "KeyMap": "571Q",
        "CombinedResponse": "F"
      }
    },
    {
      "attributes": {
        "UID": 29727552,
        "Agency": "P",
        "Address": "3499 CHIMNEY ROCK RD",
        "CrossStreet": null,
        "CALL_TIME": 1703187660000,
        "IncidentType": "CRASH/MINOR",
        "ALARM_LEVEL": 0,
        "NO_UNITS": 1,
        "Units": "18F35D",
        "LONGITUDE": -95.476384,
        "LATITUDE": 29.727552,
        "KeyMap": "491X",
        "CombinedResponse": "P"
      }
    },
    {
      "attributes": {
        "UID": 29759377,
        "Agency": "F",
        "Address": "S VOSS RD",
        "CrossStreet": "BLK HUNTINGTON CV",
        "CALL_TIME": 1703187600000,
        "IncidentType": "EMS EVENT",
        "ALARM_LEVEL": 0,
        "NO_UNITS": 2,
        "Units": "A038,M062",
        "LONGITUDE": -95.500725,
        "LATITUDE": 29.759377,
        "KeyMap": "490M",
        "CombinedResponse": "F"
      }
    },
    {
      "attributes": {
        "UID": 29691937,
        "Agency": "F",
        "Address": "HENDON LN",
        "CrossStreet": "BLK LEAWOOD BLVD",
        "CALL_TIME": 1703187540000,
        "IncidentType": "EMS EVENT",
        "ALARM_LEVEL": 0,
        "NO_UNITS": 1,
        "Units": "A073",
        "LONGITUDE": -95.577202,
        "LATITUDE": 29.691937,
        "KeyMap": "529K",
        "CombinedResponse": "F"
      }
    },
    {
      "attributes": {
        "UID": 29934408,
        "Agency": "F",
        "Address": "PLAZA VERDE DR",
        "CrossStreet": "BLK GREENS CROSSING BLVD",
        "CALL_TIME": 1703187540000,
        "IncidentType": "EMS EVENT",
        "ALARM_LEVEL": 0,
        "NO_UNITS": 1,
        "Units": "A031",
        "LONGITUDE": -95.415581,
        "LATITUDE": 29.934408,
        "KeyMap": "372U",
        "CombinedResponse": "F"
      }
    },
    {
      "attributes": {
        "UID": 29824599,
        "Agency": "F",
        "Address": "YALE ST",
        "CrossStreet": "BLK BLUEBERRY ST",
        "CALL_TIME": 1703187540000,
        "IncidentType": "EMS EVENT",
        "ALARM_LEVEL": 0,
        "NO_UNITS": 1,
        "Units": "M031",
        "LONGITUDE": -95.399612,
        "LATITUDE": 29.824599,
        "KeyMap": "452M",
        "CombinedResponse": "F"
      }
    },
    {
      "attributes": {
        "UID": 29694584,
        "Agency": "F",
        "Address": "KINGSBURY ST",
        "CrossStreet": "BLK CAVANAUGH ST",
        "CALL_TIME": 1703187420000,
        "IncidentType": "EMS EVENT",
        "ALARM_LEVEL": 0,
        "NO_UNITS": 1,
        "Units": "A040",
        "LONGITUDE": -95.336591,
        "LATITUDE": 29.694584,
        "KeyMap": "534J",
        "CombinedResponse": "F"
      }
    },
    {
      "attributes": {
        "UID": 29944380,
        "Agency": "F",
        "Address": "CITY VIEW PL",
        "CrossStreet": "BLK BENMAR DR",
        "CALL_TIME": 1703187360000,
        "IncidentType": "EMS EVENT",
        "ALARM_LEVEL": 0,
        "NO_UNITS": 1,
        "Units": "A074",
        "LONGITUDE": -95.399858,
        "LATITUDE": 29.94438,
        "KeyMap": "373N",
        "CombinedResponse": "F"
      }
    },
    {
      "attributes": {
        "UID": 29671339,
        "Agency": "F",
        "Address": "WINKLER DR",
        "CrossStreet": "BLK JULIABORA ST",
        "CALL_TIME": 1703187060000,
        "IncidentType": "EMS EVENT",
        "ALARM_LEVEL": 0,
        "NO_UNITS": 1,
        "Units": "M029",
        "LONGITUDE": -95.26156,
        "LATITUDE": 29.671339,
        "KeyMap": "535Y",
        "CombinedResponse": "F"
      }
    },
    {
      "attributes": {
        "UID": 29723518,
        "Agency": "F",
        "Address": "SOUTH FWY OB",
        "CrossStreet": "BLK SOUTHMORE BLVD",
        "CALL_TIME": 1703186880000,
        "IncidentType": "MOTOR VEHICLE INCIDENT",
        "ALARM_LEVEL": 0,
        "NO_UNITS": 1,
        "Units": "A025",
        "LONGITUDE": -95.377214,
        "LATITUDE": 29.723518,
        "KeyMap": "533B",
        "CombinedResponse": "F"
      }
    },
    {
      "attributes": {
        "UID": 29616663,
        "Agency": "P",
        "Address": "13299 SCOTT ST",
        "CrossStreet": null,
        "CALL_TIME": 1703186580000,
        "IncidentType": "CRASH/MAJOR/FSRA",
        "ALARM_LEVEL": 0,
        "NO_UNITS": 1,
        "Units": "14D25D",
        "LONGITUDE": -95.368011,
        "LATITUDE": 29.616663,
        "KeyMap": "573Q",
        "CombinedResponse": "P"
      }
    },
    {
      "attributes": {
        "UID": 29837370,
        "Agency": "F",
        "Address": "KEELAND ST",
        "CrossStreet": "BLK EASTEX FWY IB",
        "CALL_TIME": 1703186340000,
        "IncidentType": "EMS EVENT",
        "ALARM_LEVEL": 0,
        "NO_UNITS": 1,
        "Units": "A030",
        "LONGITUDE": -95.336604,
        "LATITUDE": 29.83737,
        "KeyMap": "454F",
        "CombinedResponse": "F"
      }
    },
    {
      "attributes": {
        "UID": 29987418,
        "Agency": "P",
        "Address": "3500 N TERMINAL RD",
        "CrossStreet": "S TERMINAL TOWARD N TERMINAL RAMP",
        "CALL_TIME": 1703186280000,
        "IncidentType": "CRASH/MINOR",
        "ALARM_LEVEL": 0,
        "NO_UNITS": 2,
        "Units": "21I33D,21I30D",
        "LONGITUDE": -95.339408,
        "LATITUDE": 29.987418,
        "KeyMap": "334X",
        "CombinedResponse": "P"
      }
    },
    {
      "attributes": {
        "UID": 29822366,
        "Agency": "F",
        "Address": "KEMPWOOD DR",
        "CrossStreet": "BLK ROSEFIELD DR",
        "CALL_TIME": 1703186100000,
        "IncidentType": "EMS EVENT",
        "ALARM_LEVEL": 0,
        "NO_UNITS": 1,
        "Units": "A077",
        "LONGITUDE": -95.536574,
        "LATITUDE": 29.822366,
        "KeyMap": "450K",
        "CombinedResponse": "F"
      }
    },
    {
      "attributes": {
        "UID": 29685854,
        "Agency": "P",
        "Address": "5403 GRAPE ST",
        "CrossStreet": "BLK ATWELL DR",
        "CALL_TIME": 1703185920000,
        "IncidentType": "CRASH/MINOR/FSGI",
        "ALARM_LEVEL": 0,
        "NO_UNITS": 1,
        "Units": "15E10B",
        "LONGITUDE": -95.47954,
        "LATITUDE": 29.685854,
        "KeyMap": "531P",
        "CombinedResponse": "P"
      }
    },
    {
      "attributes": {
        "UID": 29747784,
        "Agency": "P",
        "Address": "901 HADLEY ST",
        "CrossStreet": null,
        "CALL_TIME": 1703185800000,
        "IncidentType": "CRASH/MAJOR/NON FATAL",
        "ALARM_LEVEL": 0,
        "NO_UNITS": 1,
        "Units": "10H43D",
        "LONGITUDE": -95.373483,
        "LATITUDE": 29.747784,
        "KeyMap": "493P",
        "CombinedResponse": "P"
      }
    },
    {
      "attributes": {
        "UID": 29605395,
        "Agency": "F",
        "Address": "S SAM HOUSTON PKWY W",
        "CrossStreet": null,
        "CALL_TIME": 1703185740000,
        "IncidentType": "EMS EVENT",
        "ALARM_LEVEL": 0,
        "NO_UNITS": 1,
        "Units": "A047",
        "LONGITUDE": -95.477365,
        "LATITUDE": 29.605395,
        "KeyMap": "571T",
        "CombinedResponse": "F"
      }
    },
    {
      "attributes": {
        "UID": 29540253,
        "Agency": "P",
        "Address": "1601 MIDBROOK DR",
        "CrossStreet": null,
        "CALL_TIME": 1703184900000,
        "IncidentType": "CRASH/MAJOR/NON FATAL",
        "ALARM_LEVEL": 0,
        "NO_UNITS": 1,
        "Units": "12D91",
        "LONGITUDE": -95.151368,
        "LATITUDE": 29.540253,
        "KeyMap": "617Z",
        "CombinedResponse": "P"
      }
    },
    {
      "attributes": {
        "UID": 29675082,
        "Agency": "F",
        "Address": "WOODFAIR DR",
        "CrossStreet": null,
        "CALL_TIME": 1703184900000,
        "IncidentType": "EMS EVENT",
        "ALARM_LEVEL": 0,
        "NO_UNITS": 1,
        "Units": "M060",
        "LONGITUDE": -95.553658,
        "LATITUDE": 29.675082,
        "KeyMap": "529V",
        "CombinedResponse": "F"
      }
    },
    {
      "attributes": {
        "UID": 29783643,
        "Agency": "F",
        "Address": "HOFFMAN ST",
        "CrossStreet": "BLK GLENARM ST",
        "CALL_TIME": 1703184840000,
        "IncidentType": "EMS EVENT",
        "ALARM_LEVEL": 0,
        "NO_UNITS": 1,
        "Units": "M027",
        "LONGITUDE": -95.310481,
        "LATITUDE": 29.783643,
        "KeyMap": "494D",
        "CombinedResponse": "F"
      }
    },
    {
      "attributes": {
        "UID": 29598375,
        "Agency": "F",
        "Address": "S SAM HOUSTON PKWY E",
        "CrossStreet": "BLK BRUNSWICK XING",
        "CALL_TIME": 1703184660000,
        "IncidentType": "EMS EVENT",
        "ALARM_LEVEL": 0,
        "NO_UNITS": 1,
        "Units": "M055",
        "LONGITUDE": -95.365154,
        "LATITUDE": 29.598375,
        "KeyMap": "573Y",
        "CombinedResponse": "F"
      }
    },
    {
      "attributes": {
        "UID": 29714582,
        "Agency": "P",
        "Address": "8300 SANDS POINT DR",
        "CrossStreet": "BLK BURNING TREE DR",
        "CALL_TIME": 1703184060000,
        "IncidentType": "CRASH/MINOR/FSGI",
        "ALARM_LEVEL": 0,
        "NO_UNITS": 1,
        "Units": "18F52E",
        "LONGITUDE": -95.532855,
        "LATITUDE": 29.714582,
        "KeyMap": "530B",
        "CombinedResponse": "P"
      }
    },
    {
      "attributes": {
        "UID": 29846072,
        "Agency": "F",
        "Address": "OAKHAVEN LN",
        "CrossStreet": "BLK FALLEN OAKS DR",
        "CALL_TIME": 1703183580000,
        "IncidentType": "EMS EVENT",
        "ALARM_LEVEL": 0,
        "NO_UNITS": 1,
        "Units": "A034",
        "LONGITUDE": -95.469754,
        "LATITUDE": 29.846072,
        "KeyMap": "451C",
        "CombinedResponse": "F"
      }
    },
    {
      "attributes": {
        "UID": 29810931,
        "Agency": "F",
        "Address": "HAMMERLY BLVD",
        "CrossStreet": "BLK HOLLISTER ST",
        "CALL_TIME": 1703182860000,
        "IncidentType": "EMS EVENT",
        "ALARM_LEVEL": 0,
        "NO_UNITS": 1,
        "Units": "M009",
        "LONGITUDE": -95.502507,
        "LATITUDE": 29.810931,
        "KeyMap": "450R",
        "CombinedResponse": "F"
      }
    },
    {
      "attributes": {
        "UID": 29691939,
        "Agency": "P",
        "Address": "7999 SOUTHWEST FWY IB",
        "CrossStreet": null,
        "CALL_TIME": 1703182680000,
        "IncidentType": "CRASH/MAJOR/FSRA",
        "ALARM_LEVEL": 0,
        "NO_UNITS": 1,
        "Units": "76E70",
        "LONGITUDE": -95.526672,
        "LATITUDE": 29.691939,
        "KeyMap": "530K",
        "CombinedResponse": "P"
      }
    },
    {
      "attributes": {
        "UID": 29822274,
        "Agency": "F",
        "Address": "BLANKENSHIP DR",
        "CrossStreet": "BLK LAZY SPRING DR",
        "CALL_TIME": 1703182200000,
        "IncidentType": "EMS EVENT",
        "ALARM_LEVEL": 0,
        "NO_UNITS": 1,
        "Units": "A002",
        "LONGITUDE": -95.518241,
        "LATITUDE": 29.822274,
        "KeyMap": "450L",
        "CombinedResponse": "F"
      }
    },
    {
      "attributes": {
        "UID": 29665869,
        "Agency": "F",
        "Address": "CARAVAN DR",
        "CrossStreet": "BLK HOYTE DR",
        "CALL_TIME": 1703180640000,
        "IncidentType": "MEDIUM BUILDING FILL OUT",
        "ALARM_LEVEL": 1,
        "NO_UNITS": 2,
        "Units": "E068,L068",
        "LONGITUDE": -95.534145,
        "LATITUDE": 29.665869,
        "KeyMap": "530W",
        "CombinedResponse": "F"
      }
    },
    {
      "attributes": {
        "UID": 29832510,
        "Agency": "P",
        "Address": "4911 W 43RD ST",
        "CrossStreet": null,
        "CALL_TIME": 1703179740000,
        "IncidentType": "CRASH/MAJOR/NON FATAL",
        "ALARM_LEVEL": 0,
        "NO_UNITS": 1,
        "Units": "3B13D",
        "LONGITUDE": -95.463064,
        "LATITUDE": 29.83251,
        "KeyMap": "451L",
        "CombinedResponse": "P"
      }
    },
    {
      "attributes": {
        "UID": 29690936,
        "Agency": "P",
        "Address": "7900 CAMBRIDGE ST",
        "CrossStreet": "BLK EL PASEO ST",
        "CALL_TIME": 1703177880000,
        "IncidentType": "CRASH/MINOR/FSGI",
        "ALARM_LEVEL": 0,
        "NO_UNITS": 1,
        "Units": "15E44A",
        "LONGITUDE": -95.393249,
        "LATITUDE": 29.690936,
        "KeyMap": "533N",
        "CombinedResponse": "P"
      }
    },
    {
      "attributes": {
        "UID": 29772187,
        "Agency": "F",
        "Address": "VERNON ST",
        "CrossStreet": "DEAD-END",
        "CALL_TIME": 1703174520000,
        "IncidentType": "MEDIUM BUILDING FILL OUT",
        "ALARM_LEVEL": 1,
        "NO_UNITS": 2,
        "Units": "E017,E027",
        "LONGITUDE": -95.322495,
        "LATITUDE": 29.772187,
        "KeyMap": "494G",
        "CombinedResponse": "F"
      }
    }
  ]
}
