{
  "displayFieldName": "Agency",
  "fieldAliases": {
    "UID": "UID",
    "Agency": "Agency",
    "Address": "Address",
    "CrossStreet": "CrossStreet",
    "CALL_TIME": "CALL_TIME",
    "IncidentType": "IncidentType",
    "ALARM_LEVEL": "ALARM_LEVEL",
    "NO_UNITS": "NO_UNITS",
    "Units": "Units",
    "LONGITUDE": "LONGITUDE",
    "LATITUDE": "LATITUDE",
    "KeyMap": "KeyMap",
    "CombinedResponse": "CombinedResponse"
  },
  "fields": [
    {
      "name": "UID",
      "type": "esriFieldTypeOID",
      "alias": "UID"
    },
    {
      "name": "Agency",
      "type": "esriFieldTypeString",
      "alias": "Agency",
      "length": 50
    },
    {
      "name": "Address",
      "type": "esriFieldTypeString",
      "alias": "Address",
      "length": 300
    },
    {
      "name": "CrossStreet",
      "type": "esriFieldTypeString",
      "alias": "CrossStreet",
      "length": 300
    },
    {
      "name": "CALL_TIME",
      "type": "esriFieldTypeDate",
      "alias": "CALL_TIME",
      "length": 8
    },
    {
      "name": "IncidentType",
      "type": "esriFieldTypeString",
      "alias": "IncidentType",
      "length": 300
    },
    {
      "name": "ALARM_LEVEL",
      "type": "esriFieldTypeInteger",
      "alias": "ALARM_LEVEL"
    },
    {
      "name": "NO_UNITS",
      "type": "esriFieldTypeInteger",
      "alias": "NO_UNITS"
    },
    {
      "name": "Units",
      "type": "esriFieldTypeString",
      "alias": "Units",
      "length": 500
    },
    {
      "name": "LONGITUDE",
      "type": "esriFieldTypeDouble",
      "alias": "LONGITUDE"
    },
    {
      "name": "LATITUDE",
      "type": "esriFieldTypeDouble",
      "alias": "LATITUDE"
    },
    {
      "name": "KeyMap",
      "type": "esriFieldTypeString",
      "alias": "KeyMap",
      "length": 50
    },
    {
      "name": "CombinedResponse",
      "type": "esriFieldTypeString",
      "alias": "CombinedResponse",
      "length": 50
    }
  ],
  "features": [
    {
      "attributes": {
        "UID": 29731499,
        "Agency": "F",
        "Address": "WOODLAND PARK DR",
        "CrossStreet": "BLK RICHMOND AVE",
        "CALL_TIME": 1731304020000,
        "IncidentType": "EMS EVENT",
        "ALARM_LEVEL": 0,
        "NO_UNITS": 4,
        "Units": "E075,A083,M075,AS069",
        "LONGITUDE": -95.580575,
        "LATITUDE": 29.731499,
        "KeyMap": "489X",
        "CombinedResponse": "F"
      }
    },
    {
      "attributes": {
        "UID": 29834740,
        "Agency": "F",
        "Address": "SOMMERVILLE AVE",
        "CrossStreet": "BLK TERRACE MANOR DR",
        "CALL_TIME": 1731304020000,
        "IncidentType": "EMS EVENT",
        "ALARM_LEVEL": 0,
        "NO_UNITS": 2,
        "Units": "A077,M049",
        "LONGITUDE": -95.549113,
        "LATITUDE": 29.83474,
        "KeyMap": "449H",
        "CombinedResponse": "F"
      }
    },
    {
      "attributes": {
        "UID": 29786340,
        "Agency": "F",
        "Address": "FORCE ST",
        "CrossStreet": "BLK ZOE ST",
        "CALL_TIME": 1731304020000,
        "IncidentType": "EMS EVENT",
        "ALARM_LEVEL": 0,
        "NO_UNITS": 1,
        "Units": "A027",
        "LONGITUDE": -95.305034,
        "LATITUDE": 29.78634,
        "KeyMap": "494D",
        "CombinedResponse": "F"
      }
    },
    {
      "attributes": {
        "UID": 29616645,
        "Agency": "F",
        "Address": "ALMEDA GENOA RD",
        "CrossStreet": "BLK CULLEN BLVD",
        "CALL_TIME": 1731303960000,
        "IncidentType": "EMS EVENT",
        "ALARM_LEVEL": 0,
        "NO_UNITS": 1,
        "Units": "A055",
        "LONGITUDE": -95.359654,
        "LATITUDE": 29.616645,
        "KeyMap": "573Q",
        "CombinedResponse": "F"
      }
    },
    {
      "attributes": {
        "UID": 29722557,
        "Agency": "F",
        "Address": "SOUTH FWY OB",
        "CrossStreet": null,
        "CALL_TIME": 1731303900000,
        "IncidentType": "EMS EVENT",
        "ALARM_LEVEL": 0,
        "NO_UNITS": 2,
        "Units": "L007,E007",
        "LONGITUDE": -95.377555,
        "LATITUDE": 29.722557,
        "KeyMap": "533B",
        "CombinedResponse": "F"
      }
    },
    {
      "attributes": {
        "UID": 29740215,
        "Agency": "P",
        "Address": "6819 AVENUE F",
        "CrossStreet": "BLK SSGT MACARIO GARCIA DR",
        "CALL_TIME": 1731303900000,
        "IncidentType": "CRASH/MINOR",
        "ALARM_LEVEL": 0,
        "NO_UNITS": 1,
        "Units": "11H12N",
        "LONGITUDE": -95.304444,
        "LATITUDE": 29.740215,
        "KeyMap": "494V",
        "CombinedResponse": "P"
      }
    },
    {
      "attributes": {
        "UID": 29699409,
        "Agency": "F",
        "Address": "ROWAN LN",
        "CrossStreet": "BLK BRAEWICK DR",
        "CALL_TIME": 1731303840000,
        "IncidentType": "EMS EVENT",
        "ALARM_LEVEL": 0,
        "NO_UNITS": 1,
        "Units": "A051",
        "LONGITUDE": -95.49379,
        "LATITUDE": 29.699409,
        "KeyMap": "531J",
        "CombinedResponse": "F"
      }
    },
    {
      "attributes": {
        "UID": 29944500,
        "Agency": "F",
        "Address": "JOHN F KENNEDY BLVD IB",
        "CrossStreet": "BW 8 TWY",
        "CALL_TIME": 1731303780000,
        "IncidentType": "EMS EVENT",
        "ALARM_LEVEL": 0,
        "NO_UNITS": 2,
        "Units": "A064,M063",
        "LONGITUDE": -95.331779,
        "LATITUDE": 29.9445,
        "KeyMap": "374P",
        "CombinedResponse": "F"
      }
    },
    {
      "attributes": {
        "UID": 29861757,
        "Agency": "F",
        "Address": "HOLLISTER ST",
        "CrossStreet": "BLK NORTHCOURT RD",
        "CALL_TIME": 1731303780000,
        "IncidentType": "CHECK PATIENT*",
        "ALARM_LEVEL": 0,
        "NO_UNITS": 1,
        "Units": "E004",
        "LONGITUDE": -95.505434,
        "LATITUDE": 29.861757,
        "KeyMap": "410Z",
        "CombinedResponse": "F"
      }
    },
    {
      "attributes": {
        "UID": 29712219,
        "Agency": "F",
        "Address": "GULF FWY IB",
        "CrossStreet": "GRIGGS ENTR",
        "CALL_TIME": 1731303780000,
        "IncidentType": "EMS EVENT",
        "ALARM_LEVEL": 0,
        "NO_UNITS": 1,
        "Units": "E040",
        "LONGITUDE": -95.310289,
        "LATITUDE": 29.712219,
        "KeyMap": "534H",
        "CombinedResponse": "F"
      }
    },
    {
      "attributes": {
        "UID": 29656136,
        "Agency": "F",
        "Address": "CHESTERFIELD DR",
        "CrossStreet": "BLK WILMINGTON ST",
        "CALL_TIME": 1731303780000,
        "IncidentType": "EMS EVENT",
        "ALARM_LEVEL": 0,
        "NO_UNITS": 1,
        "Units": "HME024",
        "LONGITUDE": -95.372989,
        "LATITUDE": 29.656136,
        "KeyMap": "573B",
        "CombinedResponse": "F"
      }
    },
    {
      "attributes": {
        "UID": 29734868,
        "Agency": "F",
        "Address": "BRIARHURST DR",
        "CrossStreet": "DEAD-END",
        "CALL_TIME": 1731303780000,
        "IncidentType": "APARTMENT FIRE",
        "ALARM_LEVEL": 1,
        "NO_UNITS": 10,
        "Units": "E051,E003,L028,L051,D068,A060,M010,SF057,E060,D028",
        "LONGITUDE": -95.492792,
        "LATITUDE": 29.734868,
        "KeyMap": "491S",
        "CombinedResponse": "F"
      }
    },
    {
      "attributes": {
        "UID": 29596755,
        "Agency": "F",
        "Address": "S SAM HOUSTON PKWY W",
        "CrossStreet": "ALMEDA ENTR",
        "CALL_TIME": 1731303720000,
        "IncidentType": "EMS EVENT",
        "ALARM_LEVEL": 0,
        "NO_UNITS": 1,
        "Units": "E047",
        "LONGITUDE": -95.426324,
        "LATITUDE": 29.596755,
        "KeyMap": "572X",
        "CombinedResponse": "F"
      }
    },
    {
      "attributes": {
        "UID": 29726794,
        "Agency": "F",
        "Address": "SCHARPE ST",
        "CrossStreet": "BLK BROADMOOR ST",
        "CALL_TIME": 1731303540000,
        "IncidentType": "EMS EVENT",
        "ALARM_LEVEL": 0,
        "NO_UNITS": 1,
        "Units": "M018",
        "LONGITUDE": -95.331577,
        "LATITUDE": 29.726794,
        "KeyMap": "494X",
        "CombinedResponse": "F"
      }
    },
    {
      "attributes": {
        "UID": 29669986,
        "Agency": "F",
        "Address": "BROADWAY ST",
        "CrossStreet": "BLK ROCKHILL ST",
        "CALL_TIME": 1731303360000,
        "IncidentType": "EMS EVENT",
        "ALARM_LEVEL": 0,
        "NO_UNITS": 1,
        "Units": "A052",
        "LONGITUDE": -95.277034,
        "LATITUDE": 29.669986,
        "KeyMap": "535X",
        "CombinedResponse": "F"
      }
    },
    {
      "attributes": {
        "UID": 29777068,
        "Agency": "F",
        "Address": "WOOD SHADOWS DR",
        "CrossStreet": "BLK FALLOON LN",
        "CALL_TIME": 1731303300000,
        "IncidentType": "EMS EVENT",
        "ALARM_LEVEL": 0,
        "NO_UNITS": 1,
        "Units": "M044",
        "LONGITUDE": -95.234224,
        "LATITUDE": 29.777068,
        "KeyMap": "496F",
        "CombinedResponse": "F"
      }
    },
    {
      "attributes": {
        "UID": 29849529,
        "Agency": "P",
        "Address": "9320 EASTEX FWY OB",
        "CrossStreet": null,
        "CALL_TIME": 1731303120000,
        "IncidentType": "CRASH/MAJOR/NON FATAL",
        "ALARM_LEVEL": 0,
        "NO_UNITS": 1,
        "Units": "7C38F",
        "LONGITUDE": -95.332979,
        "LATITUDE": 29.849529,
        "KeyMap": "454B",
        "CombinedResponse": "P"
      }
    },
    {
      "attributes": {
        "UID": 29778100,
        "Agency": "F",
        "Address": "WINTERWOOD WAY",
        "CrossStreet": "DEAD-END",
        "CALL_TIME": 1731303060000,
        "IncidentType": "EMS EVENT",
        "ALARM_LEVEL": 0,
        "NO_UNITS": 2,
        "Units": "E044,M027",
        "LONGITUDE": -95.229203,
        "LATITUDE": 29.7781,
        "KeyMap": "496F",
        "CombinedResponse": "F"
      }
    },
    {
      "attributes": {
        "UID": 29790772,
        "Agency": "F",
        "Address": "N MAIN ST",
        "CrossStreet": "BLK VINCENT ST",
        "CALL_TIME": 1731302940000,
        "IncidentType": "EMS EVENT",
        "ALARM_LEVEL": 0,
        "NO_UNITS": 1,
        "Units": "A015",
        "LONGITUDE": -95.372913,
        "LATITUDE": 29.790772,
        "KeyMap": "453Y",
        "CombinedResponse": "F"
      }
    },
    {
      "attributes": {
        "UID": 29685270,
        "Agency": "P",
        "Address": "2099 HOLLY HALL ST",
        "CrossStreet": null,
        "CALL_TIME": 1731302880000,
        "IncidentType": "CRASH/MAJOR/CITY VEH",
        "ALARM_LEVEL": 0,
        "NO_UNITS": 3,
        "Units": "75Y03,3Z01N,70Z82N",
        "LONGITUDE": -95.399983,
        "LATITUDE": 29.68527,
        "KeyMap": "532R",
        "CombinedResponse": "P"
      }
    },
    {
      "attributes": {
        "UID": 29826022,
        "Agency": "F",
        "Address": "SCHULLER RD",
        "CrossStreet": "BLK E CROSSTIMBERS ST",
        "CALL_TIME": 1731302820000,
        "IncidentType": "EMS EVENT",
        "ALARM_LEVEL": 0,
        "NO_UNITS": 1,
        "Units": "A030",
        "LONGITUDE": -95.340669,
        "LATITUDE": 29.826022,
        "KeyMap": "454J",
        "CombinedResponse": "F"
      }
    },
    {
      "attributes": {
        "UID": 29698545,
        "Agency": "F",
        "Address": "PECAN ST",
        "CrossStreet": "BLK ANTOINETTE ST",
        "CALL_TIME": 1731302820000,
        "IncidentType": "EMS EVENT",
        "ALARM_LEVEL": 0,
        "NO_UNITS": 2,
        "Units": "M036,A018",
        "LONGITUDE": -95.307267,
        "LATITUDE": 29.698545,
        "KeyMap": "534M",
        "CombinedResponse": "F"
      }
    },
    {
      "attributes": {
        "UID": 29691300,
        "Agency": "P",
        "Address": "1499 LA CONCHA LN",
        "CrossStreet": null,
        "CALL_TIME": 1731302820000,
        "IncidentType": "CRASH/UNK MAJOR/MINOR",
        "ALARM_LEVEL": 0,
        "NO_UNITS": 1,
        "Units": "15E43N",
        "LONGITUDE": -95.407782,
        "LATITUDE": 29.6913,
        "KeyMap": "532R",
        "CombinedResponse": "P"
      }
    },
    {
      "attributes": {
        "UID": 29613481,
        "Agency": "P",
        "Address": "3815 W FUQUA ST",
        "CrossStreet": "BLK BATHURST DR",
        "CALL_TIME": 1731302760000,
        "IncidentType": "CRASH/MINOR",
        "ALARM_LEVEL": 0,
        "NO_UNITS": 2,
        "Units": "16E15N,16E11C",
        "LONGITUDE": -95.43424,
        "LATITUDE": 29.613481,
        "KeyMap": "572S",
        "CombinedResponse": "P"
      }
    },
    {
      "attributes": {
        "UID": 29667573,
        "Agency": "F",
        "Address": "LYNDHURST DR",
        "CrossStreet": "DEAD-END",
        "CALL_TIME": 1731302760000,
        "IncidentType": "EMS EVENT",
        "ALARM_LEVEL": 0,
        "NO_UNITS": 1,
        "Units": "A036",
        "LONGITUDE": -95.319905,
        "LATITUDE": 29.667573,
        "KeyMap": "534Y",
        "CombinedResponse": "F"
      }
    },
    {
      "attributes": {
        "UID": 29844901,
        "Agency": "F",
        "Address": "ANTOINE DR",
        "CrossStreet": "BLK W TIDWELL RD",
        "CALL_TIME": 1731302340000,
        "IncidentType": "EMS EVENT",
        "ALARM_LEVEL": 0,
        "NO_UNITS": 1,
        "Units": "M050",
        "LONGITUDE": -95.473255,
        "LATITUDE": 29.844901,
        "KeyMap": "451C",
        "CombinedResponse": "F"
      }
    },
    {
      "attributes": {
        "UID": 29812240,
        "Agency": "P",
        "Address": "2803 YALE ST",
        "CrossStreet": "BLK N LOOP",
        "CALL_TIME": 1731302280000,
        "IncidentType": "TRAFFIC HAZARD/URGENT",
        "ALARM_LEVEL": 0,
        "NO_UNITS": 1,
        "Units": "3B33N",
        "LONGITUDE": -95.399402,
        "LATITUDE": 29.81224,
        "KeyMap": "452R",
        "CombinedResponse": "P"
      }
    },
    {
      "attributes": {
        "UID": 29698960,
        "Agency": "F",
        "Address": "OLD SPANISH TRL",
        "CrossStreet": "BLK BURGESS ST",
        "CALL_TIME": 1731302220000,
        "IncidentType": "FIRE EVENT",
        "ALARM_LEVEL": 0,
        "NO_UNITS": 1,
        "Units": "E025",
        "LONGITUDE": -95.386403,
        "LATITUDE": 29.69896,
        "KeyMap": "533J",
        "CombinedResponse": "F"
      }
    },
    {
      "attributes": {
        "UID": 29566659,
        "Agency": "F",
        "Address": "GALVESTON RD",
        "CrossStreet": null,
        "CALL_TIME": 1731302160000,
        "IncidentType": "EMS EVENT",
        "ALARM_LEVEL": 0,
        "NO_UNITS": 1,
        "Units": "M094",
        "LONGITUDE": -95.145149,
        "LATITUDE": 29.566659,
        "KeyMap": "618J",
        "CombinedResponse": "F"
      }
    },
    {
      "attributes": {
        "UID": 29841659,
        "Agency": "F",
        "Address": "DEEP FOREST DR",
        "CrossStreet": "BLK GOLDEN FOREST DR",
        "CALL_TIME": 1731302040000,
        "IncidentType": "EMS EVENT",
        "ALARM_LEVEL": 0,
        "NO_UNITS": 1,
        "Units": "M067",
        "LONGITUDE": -95.475283,
        "LATITUDE": 29.841659,
        "KeyMap": "451F",
        "CombinedResponse": "F"
      }
    },
    {
      "attributes": {
        "UID": 29802261,
        "Agency": "F",
        "Address": "DES CHAUMES ST",
        "CrossStreet": "BLK VINTAGE ST",
        "CALL_TIME": 1731301980000,
        "IncidentType": "EMS EVENT",
        "ALARM_LEVEL": 0,
        "NO_UNITS": 2,
        "Units": "M019,A012",
        "LONGITUDE": -95.338632,
        "LATITUDE": 29.802261,
        "KeyMap": "454S",
        "CombinedResponse": "F"
      }
    },
    {
      "attributes": {
        "UID": 29651880,
        "Agency": "F",
        "Address": "IVYKNOLL DR",
        "CrossStreet": "BLK SANDPIPER DR",
        "CALL_TIME": 1731301920000,
        "IncidentType": "EMS EVENT",
        "ALARM_LEVEL": 0,
        "NO_UNITS": 2,
        "Units": "M080,A082",
        "LONGITUDE": -95.502458,
        "LATITUDE": 29.65188,
        "KeyMap": "570D",
        "CombinedResponse": "F"
      }
    },
    {
      "attributes": {
        "UID": 29636346,
        "Agency": "P",
        "Address": "13998 MAIN ST OB",
        "CrossStreet": null,
        "CALL_TIME": 1731301860000,
        "IncidentType": "CRASH/MAJOR/NON FATAL",
        "ALARM_LEVEL": 0,
        "NO_UNITS": 2,
        "Units": "16E37C,16E33C",
        "LONGITUDE": -95.493021,
        "LATITUDE": 29.636346,
        "KeyMap": "571J",
        "CombinedResponse": "P"
      }
    },
    {
      "attributes": {
        "UID": 29729151,
        "Agency": "P",
        "Address": "IH610IB-SUS59OB 4507 W IH 610 FWY S",
        "CrossStreet": "WESTHEIMER EXIT",
        "CALL_TIME": 1731301860000,
        "IncidentType": "TRAFFIC HAZARD/URGENT",
        "ALARM_LEVEL": 0,
        "NO_UNITS": 1,
        "Units": "2A51N",
        "LONGITUDE": -95.460228,
        "LATITUDE": 29.729151,
        "KeyMap": "491Y",
        "CombinedResponse": "P"
      }
    },
    {
      "attributes": {
        "UID": 29685208,
        "Agency": "P",
        "Address": "9200 MAIN ST",
        "CrossStreet": "BLK BUFFALO SPEEDWAY",
        "CALL_TIME": 1731301860000,
        "IncidentType": "CRASH/MINOR",
        "ALARM_LEVEL": 0,
        "NO_UNITS": 1,
        "Units": "15E33C",
        "LONGITUDE": -95.421783,
        "LATITUDE": 29.685208,
        "KeyMap": "532P",
        "CombinedResponse": "P"
      }
    },
    {
      "attributes": {
        "UID": 29760249,
        "Agency": "F",
        "Address": "MILAM ST",
        "CrossStreet": null,
        "CALL_TIME": 1731301800000,
        "IncidentType": "EMS EVENT",
        "ALARM_LEVEL": 0,
        "NO_UNITS": 2,
        "Units": "A009,M009",
        "LONGITUDE": -95.364892,
        "LATITUDE": 29.760249,
        "KeyMap": "493L",
        "CombinedResponse": "F"
      }
    },
    {
      "attributes": {
        "UID": 29566659,
        "Agency": "P",
        "Address": "15199 GALVESTON RD",
        "CrossStreet": null,
        "CALL_TIME": 1731301740000,
        "IncidentType": "CRASH/MAJOR/NON FATAL",
        "ALARM_LEVEL": 0,
        "NO_UNITS": 1,
        "Units": "12D72N",
        "LONGITUDE": -95.145149,
        "LATITUDE": 29.566659,
        "KeyMap": "618J",
        "CombinedResponse": "P"
      }
    },
    {
      "attributes": {
        "UID": 29688364,
        "Agency": "F",
        "Address": "PURPLE LOT NRG MCNEE RD",
        "CrossStreet": "BLK LANTERN POINT DR",
        "CALL_TIME": 1731301440000,
        "IncidentType": "EMS EVENT",
        "ALARM_LEVEL": 0,
        "NO_UNITS": 1,
        "Units": "A047",
        "LONGITUDE": -95.415251,
        "LATITUDE": 29.688364,
        "KeyMap": "532Q",
        "CombinedResponse": "F"
      }
    },
    {
      "attributes": {
        "UID": 29670070,
        "Agency": "F",
        "Address": "LEAWOOD BLVD",
        "CrossStreet": "BLK SOUTH DR",
        "CALL_TIME": 1731301320000,
        "IncidentType": "EMS EVENT",
        "ALARM_LEVEL": 0,
        "NO_UNITS": 1,
        "Units": "M083",
        "LONGITUDE": -95.576999,
        "LATITUDE": 29.67007,
        "KeyMap": "529T",
        "CombinedResponse": "F"
      }
    },
    {
      "attributes": {
        "UID": 29792498,
        "Agency": "F",
        "Address": "SPILLERS LN",
        "CrossStreet": "BLK BRINWOOD DR",
        "CALL_TIME": 1731301200000,
        "IncidentType": "HOUSE ON FIRE",
        "ALARM_LEVEL": 1,
        "NO_UNITS": 1,
        "Units": "E049",
        "LONGITUDE": -95.557566,
        "LATITUDE": 29.792498,
        "KeyMap": "449Z",
        "CombinedResponse": "F"
      }
    },
    {
      "attributes": {
        "UID": 29859458,
        "Agency": "F",
        "Address": "PARKER RD",
        "CrossStreet": "BLK EDGEWORTH ST",
        "CALL_TIME": 1731300720000,
        "IncidentType": "EMS EVENT",
        "ALARM_LEVEL": 0,
        "NO_UNITS": 1,
        "Units": "A058",
        "LONGITUDE": -95.347928,
        "LATITUDE": 29.859458,
        "KeyMap": "414W",
        "CombinedResponse": "F"
      }
    },
    {
      "attributes": {
        "UID": 29749782,
        "Agency": "P",
        "Address": "2101 DALLAS ST",
        "CrossStreet": null,
        "CALL_TIME": 1731300660000,
        "IncidentType": "CRASH/MINOR",
        "ALARM_LEVEL": 0,
        "NO_UNITS": 1,
        "Units": "10H25N",
        "LONGITUDE": -95.356658,
        "LATITUDE": 29.749782,
        "KeyMap": "493R",
        "CombinedResponse": "P"
      }
    },
    {
      "attributes": {
        "UID": 29636539,
        "Agency": "F",
        "Address": "JUDWIN ST",
        "CrossStreet": "BLK RADIO RD",
        "CALL_TIME": 1731300480000,
        "IncidentType": "EMS EVENT",
        "ALARM_LEVEL": 0,
        "NO_UNITS": 1,
        "Units": "M070",
        "LONGITUDE": -95.259592,
        "LATITUDE": 29.636539,
        "KeyMap": "575M",
        "CombinedResponse": "F"
      }
    },
    {
      "attributes": {
        "UID": 29821488,
        "Agency": "P",
        "Address": "11404 NORTHWEST FWY OB",
        "CrossStreet": "BLK MILWEE ST",
        "CALL_TIME": 1731300120000,
        "IncidentType": "CRASH/MINOR/FSGI",
        "ALARM_LEVEL": 0,
        "NO_UNITS": 1,
        "Units": "3B14N",
        "LONGITUDE": -95.470366,
        "LATITUDE": 29.821488,
        "KeyMap": "451Q",
        "CombinedResponse": "P"
      }
    },
    {
      "attributes": {
        "UID": 29812638,
        "Agency": "P",
        "Address": "100 N LOOP",
        "CrossStreet": null,
        "CALL_TIME": 1731300060000,
        "IncidentType": "CRASH/MINOR",
        "ALARM_LEVEL": 0,
        "NO_UNITS": 1,
        "Units": "2A12N",
        "LONGITUDE": -95.399398,
        "LATITUDE": 29.812638,
        "KeyMap": "453N",
        "CombinedResponse": "P"
      }
    },
    {
      "attributes": {
        "UID": 29802819,
        "Agency": "P",
        "Address": "7799 LONG POINT RD",
        "CrossStreet": null,
        "CALL_TIME": 1731299700000,
        "IncidentType": "CRASH/MAJOR/NON FATAL",
        "ALARM_LEVEL": 0,
        "NO_UNITS": 1,
        "Units": "5F12N",
        "LONGITUDE": -95.482896,
        "LATITUDE": 29.802819,
        "KeyMap": "451T",
        "CombinedResponse": "P"
      }
    },
    {
      "attributes": {
        "UID": 29735792,
        "Agency": "F",
        "Address": "HARRISBURG BLVD",
        "CrossStreet": "BLK MAGNOLIA TC ONE DR",
        "CALL_TIME": 1731299640000,
        "IncidentType": "EMS EVENT",
        "ALARM_LEVEL": 0,
        "NO_UNITS": 1,
        "Units": "A023",
        "LONGITUDE": -95.302922,
        "LATITUDE": 29.735792,
        "KeyMap": "494Z",
        "CombinedResponse": "F"
      }
    },
    {
      "attributes": {
        "UID": 29672769,
        "Agency": "F",
        "Address": "COURT GLEN DR",
        "CrossStreet": "BLK LARKDALE DR",
        "CALL_TIME": 1731299580000,
        "IncidentType": "EMS EVENT",
        "ALARM_LEVEL": 0,
        "NO_UNITS": 1,
        "Units": "A073",
        "LONGITUDE": -95.583025,
        "LATITUDE": 29.672769,
        "KeyMap": "529T",
        "CombinedResponse": "F"
      }
    },
    {
      "attributes": {
        "UID": 29650979,
        "Agency": "F",
        "Address": "E EDGEBROOK DR",
        "CrossStreet": "BLK FREETON ST",
        "CALL_TIME": 1731299460000,
        "IncidentType": "EMS EVENT",
        "ALARM_LEVEL": 0,
        "NO_UNITS": 1,
        "Units": "E052",
        "LONGITUDE": -95.212898,
        "LATITUDE": 29.650979,
        "KeyMap": "576C",
        "CombinedResponse": "F"
      }
    },
    {
      "attributes": {
        "UID": 29725636,
        "Agency": "P",
        "Address": "2405 RUTH ST",
        "CrossStreet": "BLK LIVE OAK ST",
        "CALL_TIME": 1731298920000,
        "IncidentType": "TRAFFIC HAZARD/NON URGENT",
        "ALARM_LEVEL": 0,
        "NO_UNITS": 1,
        "Units": "10H57N",
        "LONGITUDE": -95.371835,
        "LATITUDE": 29.725636,
        "KeyMap": "533C",
        "CombinedResponse": "P"
      }
    },
    {
      "attributes": {
        "UID": 29656638,
        "Agency": "F",
        "Address": "W BELLFORT AVE",
        "CrossStreet": "BLK SANDPIPER DR",
        "CALL_TIME": 1731298800000,
        "IncidentType": "EMS EVENT",
        "ALARM_LEVEL": 0,
        "NO_UNITS": 1,
        "Units": "A021",
        "LONGITUDE": -95.500994,
        "LATITUDE": 29.656638,
        "KeyMap": "570D",
        "CombinedResponse": "F"
      }
    },
    {
      "attributes": {
        "UID": 30055068,
        "Agency": "F",
        "Address": "EAGLE CREEK DR",
        "CrossStreet": "BLK HIGHLAND LAURELS DR",
        "CALL_TIME": 1731298560000,
        "IncidentType": "EMS EVENT",
        "ALARM_LEVEL": 0,
        "NO_UNITS": 1,
        "Units": "M102",
        "LONGITUDE": -95.1766,
        "LATITUDE": 30.055068,
        "KeyMap": "297Y",
        "CombinedResponse": "F"
      }
    },
    {
      "attributes": {
        "UID": 29731530,
        "Agency": "F",
        "Address": "RICHMOND AVE",
        "CrossStreet": "BLK BERING DR",
        "CALL_TIME": 1731298440000,
        "IncidentType": "EMS EVENT",
        "ALARM_LEVEL": 0,
        "NO_UNITS": 2,
        "Units": "M060,A028",
        "LONGITUDE": -95.479273,
        "LATITUDE": 29.73153,
        "KeyMap": "491X",
        "CombinedResponse": "F"
      }
    },
    {
      "attributes": {
        "UID": 29701809,
        "Agency": "F",
        "Address": "OLD SPANISH TRL",
        "CrossStreet": "BLK CULBERSON ST",
        "CALL_TIME": 1731298320000,
        "IncidentType": "EMS EVENT",
        "ALARM_LEVEL": 0,
        "NO_UNITS": 1,
        "Units": "A026",
        "LONGITUDE": -95.36793,
        "LATITUDE": 29.701809,
        "KeyMap": "533L",
        "CombinedResponse": "F"
      }
    },
    {
      "attributes": {
        "UID": 29732009,
        "Agency": "F",
        "Address": "E GREENWAY PLAZA DR",
        "CrossStreet": "BLK NORFOLK ST",
        "CALL_TIME": 1731298260000,
        "IncidentType": "EMS EVENT",
        "ALARM_LEVEL": 0,
        "NO_UNITS": 1,
        "Units": "A038",
        "LONGITUDE": -95.436532,
        "LATITUDE": 29.732009,
        "KeyMap": "492W",
        "CombinedResponse": "F"
      }
    },
    {
      "attributes": {
        "UID": 29704542,
        "Agency": "P",
        "Address": "7302 BELLAIRE BLVD",
        "CrossStreet": "BLK SHARPSTOWN CENTER",
        "CALL_TIME": 1731297480000,
        "IncidentType": "CRASH/MINOR",
        "ALARM_LEVEL": 0,
        "NO_UNITS": 1,
        "Units": "18F47N",
        "LONGITUDE": -95.513576,
        "LATITUDE": 29.704542,
        "KeyMap": "530G",
        "CombinedResponse": "P"
      }
    },
    {
      "attributes": {
        "UID": 29843936,
        "Agency": "F",
        "Address": "SHADY DR",
        "CrossStreet": "BLK FIRNAT ST",
        "CALL_TIME": 1731297420000,
        "IncidentType": "EMS EVENT",
        "ALARM_LEVEL": 0,
        "NO_UNITS": 1,
        "Units": "A034",
        "LONGITUDE": -95.308684,
        "LATITUDE": 29.843936,
        "KeyMap": "454H",
        "CombinedResponse": "F"
      }
    },
    {
      "attributes": {
        "UID": 29754398,
        "Agency": "F",
        "Address": "SANDY SPRINGS RD",
        "CrossStreet": "BLK LYNBROOK DR",
        "CALL_TIME": 1731296760000,
        "IncidentType": "EMS EVENT",
        "ALARM_LEVEL": 0,
        "NO_UNITS": 1,
        "Units": "A069",
        "LONGITUDE": -95.574423,
        "LATITUDE": 29.754398,
        "KeyMap": "489P",
        "CombinedResponse": "F"
      }
    },
    {
      "attributes": {
        "UID": 29679870,
        "Agency": "P",
        "Address": "8201 BISSONNET ST",
        "CrossStreet": null,
        "CALL_TIME": 1731295080000,
        "IncidentType": "CRASH/MAJOR/NON FATAL",
        "ALARM_LEVEL": 0,
        "NO_UNITS": 1,
        "Units": "17E21E",
        "LONGITUDE": -95.522482,
        "LATITUDE": 29.67987,
        "KeyMap": "530T",
        "CombinedResponse": "P"
      }
    },
    {
      "attributes": {
        "UID": 29938170,
        "Agency": "P",
        "Address": "11899 GREENSPOINT DR",
        "CrossStreet": null,
        "CALL_TIME": 1731295020000,
        "IncidentType": "CRASH/MAJOR/CITY VEH",
        "ALARM_LEVEL": 0,
        "NO_UNITS": 5,
        "Units": "3Z07N,70Z55N,70Z85N,70Z65N,3Z02N",
        "LONGITUDE": -95.407462,
        "LATITUDE": 29.93817,
        "KeyMap": "372V",
        "CombinedResponse": "P"
      }
    },
    {
      "attributes": {
        "UID": 29898010,
        "Agency": "P",
        "Address": "1419 W MOUNT HOUSTON RD",
        "CrossStreet": "BLK VETERANS MEMORIAL DR",
        "CALL_TIME": 1731291480000,
        "IncidentType": "CRASH/MINOR/FSGI",
        "ALARM_LEVEL": 0,
        "NO_UNITS": 1,
        "Units": "6B47N",
        "LONGITUDE": -95.425821,
        "LATITUDE": 29.89801,
        "KeyMap": "412K",
        "CombinedResponse": "P"
      }
    },
    {
      "attributes": {
        "UID": 29683437,
        "Agency": "P",
        "Address": "8316 BONNER DR",
        "CrossStreet": "BLK NEAL ST",
        "CALL_TIME": 1731291000000,
        "IncidentType": "CRASH/MINOR/FSGI",
        "ALARM_LEVEL": 0,
        "NO_UNITS": 1,
        "Units": "11H14N",
        "LONGITUDE": -95.260921,
        "LATITUDE": 29.683437,
        "KeyMap": "535Q",
        "CombinedResponse": "P"
      }
    },
    {
      "attributes": {
        "UID": 29726138,
        "Agency": "P",
        "Address": "6100 SOUTHWEST FWY OB",
        "CrossStreet": "BLK WINDSWEPT LN",
        "CALL_TIME": 1731290700000,
        "IncidentType": "CRASH/MAJOR/FATALITY",
        "ALARM_LEVEL": 0,
        "NO_UNITS": 4,
        "Units": "18F47E,70Z92N,70Z69N,70Z89N",
        "LONGITUDE": -95.487222,
        "LATITUDE": 29.726138,
        "KeyMap": "491W",
        "CombinedResponse": "P"
      }
    },
    {
      "attributes": {
        "UID": 29775979,
        "Agency": "P",
        "Address": "727 GAZIN ST",
        "CrossStreet": "BLK EAST FWY IB",
        "CALL_TIME": 1731281580000,
        "IncidentType": "CRASH/MINOR",
        "ALARM_LEVEL": 0,
        "NO_UNITS": 1,
        "Units": "9C29B",
        "LONGITUDE": -95.304252,
        "LATITUDE": 29.775979,
        "KeyMap": "494H",
        "CombinedResponse": "P"
      }
    },
    {
      "attributes": {
        "UID": 29954912,
        "Agency": "P",
        "Address": "EXIT 146 16230 N US 59 FWY OB",
        "CrossStreet": "RANKIN EXIT",
        "CALL_TIME": 1731229320000,
        "IncidentType": "CRASH/MAJOR/FATALITY",
        "ALARM_LEVEL": 0,
        "NO_UNITS": 2,
        "Units": "22B26N,22B23E",
        "LONGITUDE": -95.28893,
        "LATITUDE": 29.954912,
        "KeyMap": "375N",
        "CombinedResponse": "P"
      }
    }
  ]
}
