{
  "displayFieldName": "Agency",
  "fieldAliases": {
    "UID": "UID",
    "Agency": "Agency",
    "Address": "Address",
    "CrossStreet": "CrossStreet",
    "CALL_TIME": "CALL_TIME",
    "IncidentType": "IncidentType",
    "ALARM_LEVEL": "ALARM_LEVEL",
    "NO_UNITS": "NO_UNITS",
    "Units": "Units",
    "LONGITUDE": "LONGITUDE",
    "LATITUDE": "LATITUDE",
    "KeyMap": "KeyMap",
    "CombinedResponse": "CombinedResponse"
  },
  "fields": [
    {
      "name": "UID",
      "type": "esriFieldTypeOID",
      "alias": "UID"
    },
    {
      "name": "Agency",
      "type": "esriFieldTypeString",
      "alias": "Agency",
      "length": 50
    },
    {
      "name": "Address",
      "type": "esriFieldTypeString",
      "alias": "Address",
      "length": 300
    },
    {
      "name": "CrossStreet",
      "type": "esriFieldTypeString",
      "alias": "CrossStreet",
      "length": 300
    },
    {
      "name": "CALL_TIME",
      "type": "esriFieldTypeDate",
      "alias": "CALL_TIME",
      "length": 8
    },
    {
      "name": "IncidentType",
      "type": "esriFieldTypeString",
      "alias": "IncidentType",
      "length": 300
    },
    {
      "name": "ALARM_LEVEL",
      "type": "esriFieldTypeInteger",
      "alias": "ALARM_LEVEL"
    },
    {
      "name": "NO_UNITS",
      "type": "esriFieldTypeInteger",
      "alias": "NO_UNITS"
    },
    {
      "name": "Units",
      "type": "esriFieldTypeString",
      "alias": "Units",
      "length": 500
    },
    {
      "name": "LONGITUDE",
      "type": "esriFieldTypeDouble",
      "alias": "LONGITUDE"
    },
    {
      "name": "LATITUDE",
      "type": "esriFieldTypeDouble",
      "alias": "LATITUDE"
    },
    {
      "name": "KeyMap",
      "type": "esriFieldTypeString",
      "alias": "KeyMap",
      "length": 50
    },
    {
      "name": "CombinedResponse",
      "type": "esriFieldTypeString",
      "alias": "CombinedResponse",
      "length": 50
    }
  ],
  "features": [
    {
      "attributes": {
        "UID": 29768073,
        "Agency": "F",
        "Address": "BRIARHILLS PKWY",
        "CrossStreet": "BLK ROUSH RD",
        "CALL_TIME": 1725537660000,
        "IncidentType": "AUTOMATIC ALARM",
        "ALARM_LEVEL": 0,
        "NO_UNITS": 1,
        "Units": "E078",
        "LONGITUDE": -95.639705,
        "LATITUDE": 29.768073,
        "KeyMap": "488E",
        "CombinedResponse": "F"
      }
    },
    {
      "attributes": {
        "UID": 29740434,
        "Agency": "F",
        "Address": "PIPING ROCK LN",
        "CrossStreet": "BLK BRIARPORT DR",
        "CALL_TIME": 1725537660000,
        "IncidentType": "EMS EVENT",
        "ALARM_LEVEL": 0,
        "NO_UNITS": 1,
        "Units": "E086",
        "LONGITUDE": -95.639467,
        "LATITUDE": 29.740434,
        "KeyMap": "488S",
        "CombinedResponse": "F"
      }
    },
    {
      "attributes": {
        "UID": 29745650,
        "Agency": "F",
        "Address": "CANAL ST",
        "CrossStreet": "BLK ALTIC ST",
        "CALL_TIME": 1725537600000,
        "IncidentType": "EMS EVENT",
        "ALARM_LEVEL": 0,
        "NO_UNITS": 1,
        "Units": "M018",
        "LONGITUDE": -95.319268,
        "LATITUDE": 29.74565,
        "KeyMap": "494U",
        "CombinedResponse": "F"
      }
    },
    {
      "attributes": {
        "UID": 29691412,
        "Agency": "F",
        "Address": "HARTFORD ST",
        "CrossStreet": "BLK HASTINGS ST",
        "CALL_TIME": 1725537480000,
        "IncidentType": "EMS EVENT",
        "ALARM_LEVEL": 0,
        "NO_UNITS": 1,
        "Units": "A023",
        "LONGITUDE": -95.276067,
        "LATITUDE": 29.691412,
        "KeyMap": "535P",
        "CombinedResponse": "F"
      }
    },
    {
      "attributes": {
        "UID": 29772906,
        "Agency": "P",
        "Address": "IH10IB-WACO ST 4371 E IH 10 FWY IB",
        "CrossStreet": "WACO EXIT",
        "CALL_TIME": 1725537420000,
        "IncidentType": "TRAFFIC HAZARD/URGENT",
        "ALARM_LEVEL": 0,
        "NO_UNITS": 1,
        "Units": "7C48A",
        "LONGITUDE": -95.326413,
        "LATITUDE": 29.772906,
        "KeyMap": "494F",
        "CombinedResponse": "P"
      }
    },
    {
      "attributes": {
        "UID": 29608783,
        "Agency": "F",
        "Address": "GARDEN BRIDGE ST",
        "CrossStreet": "BLK GULF BRIDGE ST",
        "CALL_TIME": 1725537420000,
        "IncidentType": "EMS EVENT",
        "ALARM_LEVEL": 0,
        "NO_UNITS": 1,
        "Units": "M070",
        "LONGITUDE": -95.248828,
        "LATITUDE": 29.608783,
        "KeyMap": "575V",
        "CombinedResponse": "F"
      }
    },
    {
      "attributes": {
        "UID": 29850542,
        "Agency": "P",
        "Address": "6150 W TIDWELL RD",
        "CrossStreet": "BLK LUMBERDALE RD",
        "CALL_TIME": 1725537360000,
        "IncidentType": "CRASH/MAJOR/NON FATAL",
        "ALARM_LEVEL": 0,
        "NO_UNITS": 1,
        "Units": "8C13A",
        "LONGITUDE": -95.480786,
        "LATITUDE": 29.850542,
        "KeyMap": "451B",
        "CombinedResponse": "P"
      }
    },
    {
      "attributes": {
        "UID": 29747595,
        "Agency": "F",
        "Address": "US59IB-LEELAND N US 59 FWY IB",
        "CrossStreet": "S IH 45 ENTR",
        "CALL_TIME": 1725537360000,
        "IncidentType": "EMS EVENT",
        "ALARM_LEVEL": 0,
        "NO_UNITS": 3,
        "Units": "E017,A019,E019",
        "LONGITUDE": -95.360382,
        "LATITUDE": 29.747595,
        "KeyMap": "493Q",
        "CombinedResponse": "F"
      }
    },
    {
      "attributes": {
        "UID": 29644754,
        "Agency": "F",
        "Address": "MAIN ST IB",
        "CrossStreet": "CHIMNEY ROCK ENTR",
        "CALL_TIME": 1725537360000,
        "IncidentType": "EMS EVENT",
        "ALARM_LEVEL": 0,
        "NO_UNITS": 1,
        "Units": "A048",
        "LONGITUDE": -95.470293,
        "LATITUDE": 29.644754,
        "KeyMap": "571F",
        "CombinedResponse": "F"
      }
    },
    {
      "attributes": {
        "UID": 29784654,
        "Agency": "P",
        "Address": "IH610OB-GELLHORN 9899 N IH 610 FWY E",
        "CrossStreet": "N IH 610 OB ENTR",
        "CALL_TIME": 1725537300000,
        "IncidentType": "TRAFFIC HAZARD/URGENT",
        "ALARM_LEVEL": 0,
        "NO_UNITS": 1,
        "Units": "9C30A",
        "LONGITUDE": -95.264733,
        "LATITUDE": 29.784654,
        "KeyMap": "495C",
        "CombinedResponse": "P"
      }
    },
    {
      "attributes": {
        "UID": 29847560,
        "Agency": "F",
        "Address": "VALLEY WIND DR",
        "CrossStreet": "BLK BROCK PARK BLVD",
        "CALL_TIME": 1725537180000,
        "IncidentType": "EMS EVENT",
        "ALARM_LEVEL": 0,
        "NO_UNITS": 2,
        "Units": "M043,A032",
        "LONGITUDE": -95.240531,
        "LATITUDE": 29.84756,
        "KeyMap": "456A",
        "CombinedResponse": "F"
      }
    },
    {
      "attributes": {
        "UID": 29850542,
        "Agency": "F",
        "Address": "W TIDWELL RD",
        "CrossStreet": "BLK LUMBERDALE RD",
        "CALL_TIME": 1725537120000,
        "IncidentType": "EMS EVENT",
        "ALARM_LEVEL": 0,
        "NO_UNITS": 1,
        "Units": "E004",
        "LONGITUDE": -95.480786,
        "LATITUDE": 29.850542,
        "KeyMap": "451B",
        "CombinedResponse": "F"
      }
    },
    {
      "attributes": {
        "UID": 29808737,
        "Agency": "F",
        "Address": "ANTOINE DR",
        "CrossStreet": "BLK HAMMERLY BLVD",
        "CALL_TIME": 1725537060000,
        "IncidentType": "EMS EVENT",
        "ALARM_LEVEL": 0,
        "NO_UNITS": 1,
        "Units": "A038",
        "LONGITUDE": -95.475227,
        "LATITUDE": 29.808737,
        "KeyMap": "451T",
        "CombinedResponse": "F"
      }
    },
    {
      "attributes": {
        "UID": 29818643,
        "Agency": "F",
        "Address": "HEMPSTEAD RD",
        "CrossStreet": "BLK LUMBERDALE RD",
        "CALL_TIME": 1725537060000,
        "IncidentType": "EMS EVENT",
        "ALARM_LEVEL": 0,
        "NO_UNITS": 1,
        "Units": "A004",
        "LONGITUDE": -95.483679,
        "LATITUDE": 29.818643,
        "KeyMap": "451P",
        "CombinedResponse": "F"
      }
    },
    {
      "attributes": {
        "UID": 29863146,
        "Agency": "F",
        "Address": "W LITTLE YORK RD",
        "CrossStreet": null,
        "CALL_TIME": 1725537000000,
        "IncidentType": "EMS EVENT",
        "ALARM_LEVEL": 0,
        "NO_UNITS": 2,
        "Units": "E067,A058",
        "LONGITUDE": -95.449087,
        "LATITUDE": 29.863146,
        "KeyMap": "412W",
        "CombinedResponse": "F"
      }
    },
    {
      "attributes": {
        "UID": 29850528,
        "Agency": "P",
        "Address": "6099 W SUNFOREST DR",
        "CrossStreet": null,
        "CALL_TIME": 1725536880000,
        "IncidentType": "CRASH/MAJOR/NON FATAL",
        "ALARM_LEVEL": 0,
        "NO_UNITS": 1,
        "Units": "3B40D",
        "LONGITUDE": -95.480079,
        "LATITUDE": 29.850528,
        "KeyMap": "451B",
        "CombinedResponse": "P"
      }
    },
    {
      "attributes": {
        "UID": 29644754,
        "Agency": "P",
        "Address": "12801 MAIN ST IB",
        "CrossStreet": "CHIMNEY ROCK ENTR",
        "CALL_TIME": 1725536700000,
        "IncidentType": "CRASH/MAJOR/NON FATAL",
        "ALARM_LEVEL": 0,
        "NO_UNITS": 1,
        "Units": "16E32A",
        "LONGITUDE": -95.470293,
        "LATITUDE": 29.644754,
        "KeyMap": "571F",
        "CombinedResponse": "P"
      }
    },
    {
      "attributes": {
        "UID": 29809895,
        "Agency": "F",
        "Address": "LOCKWOOD DR",
        "CrossStreet": "BLK TROOST ST",
        "CALL_TIME": 1725536460000,
        "IncidentType": "EMS EVENT",
        "ALARM_LEVEL": 0,
        "NO_UNITS": 1,
        "Units": "A039",
        "LONGITUDE": -95.317107,
        "LATITUDE": 29.809895,
        "KeyMap": "454U",
        "CombinedResponse": "F"
      }
    },
    {
      "attributes": {
        "UID": 29848872,
        "Agency": "P",
        "Address": "ANTOINE DR",
        "CrossStreet": null,
        "CALL_TIME": 1725536280000,
        "IncidentType": "CRASH/MAJOR/NON FATAL",
        "ALARM_LEVEL": 0,
        "NO_UNITS": 2,
        "Units": "6B20D,3B10D",
        "LONGITUDE": -95.473297,
        "LATITUDE": 29.848872,
        "KeyMap": "451C",
        "CombinedResponse": "P"
      }
    },
    {
      "attributes": {
        "UID": 29662308,
        "Agency": "F",
        "Address": "WESTBRAE PKWY",
        "CrossStreet": "BLK BRAEBURN BEND DR",
        "CALL_TIME": 1725536220000,
        "IncidentType": "EMS EVENT",
        "ALARM_LEVEL": 0,
        "NO_UNITS": 1,
        "Units": "A068",
        "LONGITUDE": -95.534597,
        "LATITUDE": 29.662308,
        "KeyMap": "530W",
        "CombinedResponse": "F"
      }
    },
    {
      "attributes": {
        "UID": 29777397,
        "Agency": "P",
        "Address": "IH10IB-WASHINGTON 5963 W IH 10 FWY IB",
        "CrossStreet": "WESTCOTT - WASHINGTON EXIT",
        "CALL_TIME": 1725536100000,
        "IncidentType": "TRAFFIC HAZARD/URGENT",
        "ALARM_LEVEL": 0,
        "NO_UNITS": 4,
        "Units": "2A12D,2A60D,75Z37,75Z10",
        "LONGITUDE": -95.428869,
        "LATITUDE": 29.777397,
        "KeyMap": "492F",
        "CombinedResponse": "P"
      }
    },
    {
      "attributes": {
        "UID": 29825553,
        "Agency": "F",
        "Address": "MCKEAN DR",
        "CrossStreet": "BLK COLLEEN RD",
        "CALL_TIME": 1725535980000,
        "IncidentType": "EMS EVENT",
        "ALARM_LEVEL": 0,
        "NO_UNITS": 1,
        "Units": "A005",
        "LONGITUDE": -95.513465,
        "LATITUDE": 29.825553,
        "KeyMap": "450L",
        "CombinedResponse": "F"
      }
    },
    {
      "attributes": {
        "UID": 29824386,
        "Agency": "F",
        "Address": "JIM ST",
        "CrossStreet": "BLK HARLAND DR",
        "CALL_TIME": 1725535920000,
        "IncidentType": "EMS EVENT",
        "ALARM_LEVEL": 0,
        "NO_UNITS": 1,
        "Units": "A013",
        "LONGITUDE": -95.474782,
        "LATITUDE": 29.824386,
        "KeyMap": "451K",
        "CombinedResponse": "F"
      }
    },
    {
      "attributes": {
        "UID": 29761783,
        "Agency": "F",
        "Address": "N CHENEVERT ST",
        "CrossStreet": "N JACKSON ST",
        "CALL_TIME": 1725535800000,
        "IncidentType": "EMS EVENT",
        "ALARM_LEVEL": 0,
        "NO_UNITS": 1,
        "Units": "A017",
        "LONGITUDE": -95.351112,
        "LATITUDE": 29.761783,
        "KeyMap": "493M",
        "CombinedResponse": "F"
      }
    },
    {
      "attributes": {
        "UID": 29952940,
        "Agency": "F",
        "Address": "LANGWICK DR",
        "CrossStreet": "BLK W HARDY RD",
        "CALL_TIME": 1725535620000,
        "IncidentType": "EMS EVENT",
        "ALARM_LEVEL": 0,
        "NO_UNITS": 1,
        "Units": "A074",
        "LONGITUDE": -95.391788,
        "LATITUDE": 29.95294,
        "KeyMap": "373N",
        "CombinedResponse": "F"
      }
    },
    {
      "attributes": {
        "UID": 29952191,
        "Agency": "F",
        "Address": "GREENS RD",
        "CrossStreet": "BLK GREEN MANOR DR",
        "CALL_TIME": 1725535620000,
        "IncidentType": "EMS EVENT",
        "ALARM_LEVEL": 0,
        "NO_UNITS": 2,
        "Units": "M074,A064",
        "LONGITUDE": -95.296429,
        "LATITUDE": 29.952191,
        "KeyMap": "375N",
        "CombinedResponse": "F"
      }
    },
    {
      "attributes": {
        "UID": 29723205,
        "Agency": "F",
        "Address": "SOUTHMORE BLVD",
        "CrossStreet": null,
        "CALL_TIME": 1725535620000,
        "IncidentType": "EMS EVENT",
        "ALARM_LEVEL": 0,
        "NO_UNITS": 1,
        "Units": "A007",
        "LONGITUDE": -95.378622,
        "LATITUDE": 29.723205,
        "KeyMap": "533B",
        "CombinedResponse": "F"
      }
    },
    {
      "attributes": {
        "UID": 29723205,
        "Agency": "P",
        "Address": "2099 SOUTHMORE BLVD",
        "CrossStreet": null,
        "CALL_TIME": 1725535380000,
        "IncidentType": "CRASH/MAJOR/NON FATAL",
        "ALARM_LEVEL": 0,
        "NO_UNITS": 1,
        "Units": "10H86D",
        "LONGITUDE": -95.378622,
        "LATITUDE": 29.723205,
        "KeyMap": "533B",
        "CombinedResponse": "P"
      }
    },
    {
      "attributes": {
        "UID": 29682203,
        "Agency": "F",
        "Address": "WESTRIDGE ST",
        "CrossStreet": "BLK W BARTELL DR",
        "CALL_TIME": 1725535200000,
        "IncidentType": "EMS EVENT",
        "ALARM_LEVEL": 0,
        "NO_UNITS": 4,
        "Units": "A033,SQ033,AS016,E021",
        "LONGITUDE": -95.41923,
        "LATITUDE": 29.682203,
        "KeyMap": "532Q",
        "CombinedResponse": "F"
      }
    },
    {
      "attributes": {
        "UID": 29627213,
        "Agency": "F",
        "Address": "DAWN MISTY LN",
        "CrossStreet": "BLK PEACEFUL RIDGE DR",
        "CALL_TIME": 1725535020000,
        "IncidentType": "EMS EVENT",
        "ALARM_LEVEL": 0,
        "NO_UNITS": 1,
        "Units": "A055",
        "LONGITUDE": -95.327213,
        "LATITUDE": 29.627213,
        "KeyMap": "574P",
        "CombinedResponse": "F"
      }
    },
    {
      "attributes": {
        "UID": 29802449,
        "Agency": "F",
        "Address": "CORTLANDT ST",
        "CrossStreet": "BLK E 20TH ST",
        "CALL_TIME": 1725534900000,
        "IncidentType": "EMS EVENT",
        "ALARM_LEVEL": 0,
        "NO_UNITS": 1,
        "Units": "A015",
        "LONGITUDE": -95.395551,
        "LATITUDE": 29.802449,
        "KeyMap": "453S",
        "CombinedResponse": "F"
      }
    },
    {
      "attributes": {
        "UID": 29937708,
        "Agency": "F",
        "Address": "NBW8IB-ELLA BLVD N BW 8 TWY W",
        "CrossStreet": "T C JESTER ENTR",
        "CALL_TIME": 1725534900000,
        "IncidentType": "MOTOR VEHICLE INCIDENT",
        "ALARM_LEVEL": 0,
        "NO_UNITS": 2,
        "Units": "A084,A067",
        "LONGITUDE": -95.432226,
        "LATITUDE": 29.937708,
        "KeyMap": "372T",
        "CombinedResponse": "F"
      }
    },
    {
      "attributes": {
        "UID": 29649885,
        "Agency": "F",
        "Address": "SIERRA DR",
        "CrossStreet": "BLK CHIMIRA LN",
        "CALL_TIME": 1725534660000,
        "IncidentType": "EMS EVENT",
        "ALARM_LEVEL": 0,
        "NO_UNITS": 1,
        "Units": "A046",
        "LONGITUDE": -95.374466,
        "LATITUDE": 29.649885,
        "KeyMap": "573F",
        "CombinedResponse": "F"
      }
    },
    {
      "attributes": {
        "UID": 29711761,
        "Agency": "F",
        "Address": "TELEPHONE RD",
        "CrossStreet": "BLK WHEELER ST",
        "CALL_TIME": 1725534660000,
        "IncidentType": "EMS EVENT",
        "ALARM_LEVEL": 0,
        "NO_UNITS": 1,
        "Units": "A040",
        "LONGITUDE": -95.315371,
        "LATITUDE": 29.711761,
        "KeyMap": "534G",
        "CombinedResponse": "F"
      }
    },
    {
      "attributes": {
        "UID": 29722575,
        "Agency": "F",
        "Address": "TC HILLCROFT SOUTHWEST FWY SOUTHWEST FWY OB",
        "CrossStreet": "HILLCROFT EXIT",
        "CALL_TIME": 1725534420000,
        "IncidentType": "EMS EVENT",
        "ALARM_LEVEL": 0,
        "NO_UNITS": 1,
        "Units": "A051",
        "LONGITUDE": -95.4958,
        "LATITUDE": 29.722575,
        "KeyMap": "531A",
        "CombinedResponse": "F"
      }
    },
    {
      "attributes": {
        "UID": 29682077,
        "Agency": "F",
        "Address": "WESTRIDGE ST",
        "CrossStreet": "BLK LANTERN POINT DR",
        "CALL_TIME": 1725534240000,
        "IncidentType": "EMS EVENT",
        "ALARM_LEVEL": 0,
        "NO_UNITS": 1,
        "Units": "A037",
        "LONGITUDE": -95.413758,
        "LATITUDE": 29.682077,
        "KeyMap": "532Q",
        "CombinedResponse": "F"
      }
    },
    {
      "attributes": {
        "UID": 29782550,
        "Agency": "F",
        "Address": "KATY FWY IB",
        "CrossStreet": "SILBER ENTR",
        "CALL_TIME": 1725533520000,
        "IncidentType": "EMS EVENT",
        "ALARM_LEVEL": 0,
        "NO_UNITS": 4,
        "Units": "AS050,M062,MD001,HMSR22",
        "LONGITUDE": -95.459957,
        "LATITUDE": 29.78255,
        "KeyMap": "491D",
        "CombinedResponse": "F"
      }
    },
    {
      "attributes": {
        "UID": 29823330,
        "Agency": "P",
        "Address": "3795 ANTOINE DR",
        "CrossStreet": null,
        "CALL_TIME": 1725533220000,
        "IncidentType": "CRASH/MINOR",
        "ALARM_LEVEL": 0,
        "NO_UNITS": 1,
        "Units": "76B20D",
        "LONGITUDE": -95.473405,
        "LATITUDE": 29.82333,
        "KeyMap": "451L",
        "CombinedResponse": "P"
      }
    },
    {
      "attributes": {
        "UID": 29655538,
        "Agency": "F",
        "Address": "SOUTHWEST FWY IB",
        "CrossStreet": "BELLFORT OBIB",
        "CALL_TIME": 1725532620000,
        "IncidentType": "EMS EVENT",
        "ALARM_LEVEL": 0,
        "NO_UNITS": 1,
        "Units": "A073",
        "LONGITUDE": -95.563255,
        "LATITUDE": 29.655538,
        "KeyMap": "569C",
        "CombinedResponse": "F"
      }
    },
    {
      "attributes": {
        "UID": 29551229,
        "Agency": "P",
        "Address": "527 BAY AREA BLVD",
        "CrossStreet": "BAY AREA PR",
        "CALL_TIME": 1725530880000,
        "IncidentType": "CRASH/MINOR",
        "ALARM_LEVEL": 0,
        "NO_UNITS": 1,
        "Units": "12D50D",
        "LONGITUDE": -95.125643,
        "LATITUDE": 29.551229,
        "KeyMap": "618T",
        "CombinedResponse": "P"
      }
    },
    {
      "attributes": {
        "UID": 29776096,
        "Agency": "F",
        "Address": "PINEHAVEN DR",
        "CrossStreet": "BLK CHATSWORTH DR",
        "CALL_TIME": 1725529620000,
        "IncidentType": "EMS EVENT",
        "ALARM_LEVEL": 0,
        "NO_UNITS": 1,
        "Units": "A002",
        "LONGITUDE": -95.459717,
        "LATITUDE": 29.776096,
        "KeyMap": "491H",
        "CombinedResponse": "F"
      }
    },
    {
      "attributes": {
        "UID": 29715531,
        "Agency": "P",
        "Address": "11400 HARWIN DR",
        "CrossStreet": "BLK BAYNARD DR",
        "CALL_TIME": 1725526740000,
        "IncidentType": "TRAFFIC HAZARD/URGENT",
        "ALARM_LEVEL": 0,
        "NO_UNITS": 1,
        "Units": "19G13N",
        "LONGITUDE": -95.571506,
        "LATITUDE": 29.715531,
        "KeyMap": "529C",
        "CombinedResponse": "P"
      }
    },
    {
      "attributes": {
        "UID": 29784360,
        "Agency": "P",
        "Address": "7900 KATY FWY OB",
        "CrossStreet": null,
        "CALL_TIME": 1725519780000,
        "IncidentType": "CRASH/MAJOR/FATALITY",
        "ALARM_LEVEL": 0,
        "NO_UNITS": 10,
        "Units": "5F13N,5F10N,5F31N,4F33N,4F21N,3Z03N,70Z81N,70Z75N,70Z77N,4F04N",
        "LONGITUDE": -95.475502,
        "LATITUDE": 29.78436,
        "KeyMap": "491B",
        "CombinedResponse": "P"
      }
    }
  ]
}
